<?xml version="1.0" encoding="UTF-8"?>
<cppdepend-plugin tool="Misra">
<file path="c:\openxray\externals\opcode\opc_aabb.h"><violation beginline="134" endline="134" rule="Rule7-5-4" ruleset="Declarations">
</violation><violation beginline="136" endline="136" rule="Rule7-5-4" ruleset="Declarations">
</violation></file><file path="c:\openxray\externals\opcode\opc_matrix3x3.h"><violation beginline="21" endline="21" rule="Rule7-5-4" ruleset="Declarations">
</violation><violation beginline="653" endline="653" rule="Rule7-5-4" ruleset="Declarations">
</violation><violation beginline="653" endline="653" rule="Rule7-5-4" ruleset="Declarations">
</violation><violation beginline="653" endline="653" rule="Rule7-5-4" ruleset="Declarations">
</violation><violation beginline="653" endline="653" rule="Rule7-5-4" ruleset="Declarations">
</violation><violation beginline="653" endline="653" rule="Rule7-5-4" ruleset="Declarations">
</violation><violation beginline="653" endline="653" rule="Rule7-5-4" ruleset="Declarations">
</violation></file><file path="c:\openxray\externals\opcode\opc_matrix4x4.h"><violation beginline="387" endline="387" rule="Rule7-5-4" ruleset="Declarations">
</violation></file><file path="c:\openxray\externals\opcode\opc_obb.cpp"><violation beginline="48" endline="48" rule="Rule6-6-5" ruleset="Statements">
</violation><violation beginline="119" endline="119" rule="Rule6-6-5" ruleset="Statements">
</violation><violation beginline="148" endline="148" rule="Rule6-6-5" ruleset="Statements">
</violation></file><file path="c:\openxray\externals\opcode\opc_point.h"><violation beginline="525" endline="525" rule="Rule7-5-4" ruleset="Declarations">
</violation><violation beginline="682" endline="682" rule="Rule7-5-4" ruleset="Declarations">
</violation><violation beginline="37" endline="37" rule="Rule7-5-4" ruleset="Declarations">
</violation><violation beginline="37" endline="37" rule="Rule7-5-4" ruleset="Declarations">
</violation><violation beginline="521" endline="521" rule="Rule7-5-4" ruleset="Declarations">
</violation><violation beginline="37" endline="37" rule="Rule7-5-4" ruleset="Declarations">
</violation><violation beginline="37" endline="37" rule="Rule7-5-4" ruleset="Declarations">
</violation><violation beginline="521" endline="521" rule="Rule7-5-4" ruleset="Declarations">
</violation><violation beginline="37" endline="37" rule="Rule7-5-4" ruleset="Declarations">
</violation><violation beginline="37" endline="37" rule="Rule7-5-4" ruleset="Declarations">
</violation><violation beginline="521" endline="521" rule="Rule7-5-4" ruleset="Declarations">
</violation><violation beginline="523" endline="523" rule="Rule7-5-4" ruleset="Declarations">
</violation><violation beginline="529" endline="529" rule="Rule7-5-4" ruleset="Declarations">
</violation><violation beginline="525" endline="525" rule="Rule7-5-4" ruleset="Declarations">
</violation><violation beginline="529" endline="529" rule="Rule7-5-4" ruleset="Declarations">
</violation><violation beginline="523" endline="523" rule="Rule7-5-4" ruleset="Declarations">
</violation><violation beginline="529" endline="529" rule="Rule7-5-4" ruleset="Declarations">
</violation><violation beginline="525" endline="525" rule="Rule7-5-4" ruleset="Declarations">
</violation><violation beginline="529" endline="529" rule="Rule7-5-4" ruleset="Declarations">
</violation><violation beginline="523" endline="523" rule="Rule7-5-4" ruleset="Declarations">
</violation><violation beginline="529" endline="529" rule="Rule7-5-4" ruleset="Declarations">
</violation><violation beginline="525" endline="525" rule="Rule7-5-4" ruleset="Declarations">
</violation><violation beginline="529" endline="529" rule="Rule7-5-4" ruleset="Declarations">
</violation><violation beginline="543" endline="543" rule="Rule7-5-4" ruleset="Declarations">
</violation><violation beginline="543" endline="543" rule="Rule7-5-4" ruleset="Declarations">
</violation><violation beginline="543" endline="543" rule="Rule7-5-4" ruleset="Declarations">
</violation><violation beginline="543" endline="543" rule="Rule7-5-4" ruleset="Declarations">
</violation><violation beginline="543" endline="543" rule="Rule7-5-4" ruleset="Declarations">
</violation><violation beginline="543" endline="543" rule="Rule7-5-4" ruleset="Declarations">
</violation><violation beginline="37" endline="37" rule="Rule7-5-4" ruleset="Declarations">
</violation><violation beginline="523" endline="523" rule="Rule7-5-4" ruleset="Declarations">
</violation><violation beginline="523" endline="523" rule="Rule7-5-4" ruleset="Declarations">
</violation><violation beginline="525" endline="525" rule="Rule7-5-4" ruleset="Declarations">
</violation><violation beginline="529" endline="529" rule="Rule7-5-4" ruleset="Declarations">
</violation><violation beginline="529" endline="529" rule="Rule7-5-4" ruleset="Declarations">
</violation><violation beginline="529" endline="529" rule="Rule7-5-4" ruleset="Declarations">
</violation><violation beginline="37" endline="37" rule="Rule7-5-4" ruleset="Declarations">
</violation><violation beginline="523" endline="523" rule="Rule7-5-4" ruleset="Declarations">
</violation><violation beginline="523" endline="523" rule="Rule7-5-4" ruleset="Declarations">
</violation><violation beginline="523" endline="523" rule="Rule7-5-4" ruleset="Declarations">
</violation><violation beginline="529" endline="529" rule="Rule7-5-4" ruleset="Declarations">
</violation><violation beginline="529" endline="529" rule="Rule7-5-4" ruleset="Declarations">
</violation><violation beginline="529" endline="529" rule="Rule7-5-4" ruleset="Declarations">
</violation><violation beginline="37" endline="37" rule="Rule7-5-4" ruleset="Declarations">
</violation><violation beginline="523" endline="523" rule="Rule7-5-4" ruleset="Declarations">
</violation><violation beginline="525" endline="525" rule="Rule7-5-4" ruleset="Declarations">
</violation><violation beginline="523" endline="523" rule="Rule7-5-4" ruleset="Declarations">
</violation><violation beginline="529" endline="529" rule="Rule7-5-4" ruleset="Declarations">
</violation><violation beginline="529" endline="529" rule="Rule7-5-4" ruleset="Declarations">
</violation><violation beginline="529" endline="529" rule="Rule7-5-4" ruleset="Declarations">
</violation><violation beginline="37" endline="37" rule="Rule7-5-4" ruleset="Declarations">
</violation><violation beginline="523" endline="523" rule="Rule7-5-4" ruleset="Declarations">
</violation><violation beginline="525" endline="525" rule="Rule7-5-4" ruleset="Declarations">
</violation><violation beginline="525" endline="525" rule="Rule7-5-4" ruleset="Declarations">
</violation><violation beginline="529" endline="529" rule="Rule7-5-4" ruleset="Declarations">
</violation><violation beginline="529" endline="529" rule="Rule7-5-4" ruleset="Declarations">
</violation><violation beginline="529" endline="529" rule="Rule7-5-4" ruleset="Declarations">
</violation><violation beginline="37" endline="37" rule="Rule7-5-4" ruleset="Declarations">
</violation><violation beginline="525" endline="525" rule="Rule7-5-4" ruleset="Declarations">
</violation><violation beginline="523" endline="523" rule="Rule7-5-4" ruleset="Declarations">
</violation><violation beginline="525" endline="525" rule="Rule7-5-4" ruleset="Declarations">
</violation><violation beginline="529" endline="529" rule="Rule7-5-4" ruleset="Declarations">
</violation><violation beginline="529" endline="529" rule="Rule7-5-4" ruleset="Declarations">
</violation><violation beginline="529" endline="529" rule="Rule7-5-4" ruleset="Declarations">
</violation><violation beginline="37" endline="37" rule="Rule7-5-4" ruleset="Declarations">
</violation><violation beginline="525" endline="525" rule="Rule7-5-4" ruleset="Declarations">
</violation><violation beginline="523" endline="523" rule="Rule7-5-4" ruleset="Declarations">
</violation><violation beginline="523" endline="523" rule="Rule7-5-4" ruleset="Declarations">
</violation><violation beginline="529" endline="529" rule="Rule7-5-4" ruleset="Declarations">
</violation><violation beginline="529" endline="529" rule="Rule7-5-4" ruleset="Declarations">
</violation><violation beginline="529" endline="529" rule="Rule7-5-4" ruleset="Declarations">
</violation><violation beginline="37" endline="37" rule="Rule7-5-4" ruleset="Declarations">
</violation><violation beginline="525" endline="525" rule="Rule7-5-4" ruleset="Declarations">
</violation><violation beginline="525" endline="525" rule="Rule7-5-4" ruleset="Declarations">
</violation><violation beginline="523" endline="523" rule="Rule7-5-4" ruleset="Declarations">
</violation><violation beginline="529" endline="529" rule="Rule7-5-4" ruleset="Declarations">
</violation><violation beginline="529" endline="529" rule="Rule7-5-4" ruleset="Declarations">
</violation><violation beginline="529" endline="529" rule="Rule7-5-4" ruleset="Declarations">
</violation><violation beginline="37" endline="37" rule="Rule7-5-4" ruleset="Declarations">
</violation><violation beginline="525" endline="525" rule="Rule7-5-4" ruleset="Declarations">
</violation><violation beginline="525" endline="525" rule="Rule7-5-4" ruleset="Declarations">
</violation><violation beginline="525" endline="525" rule="Rule7-5-4" ruleset="Declarations">
</violation><violation beginline="529" endline="529" rule="Rule7-5-4" ruleset="Declarations">
</violation><violation beginline="529" endline="529" rule="Rule7-5-4" ruleset="Declarations">
</violation><violation beginline="529" endline="529" rule="Rule7-5-4" ruleset="Declarations">
</violation></file></cppdepend-plugin>