<?xml version="1.0" encoding="UTF-8"?>
<cppdepend-plugin tool="Misra">
<file path="c:\openxray\externals\bugtrap\source\client\bugtraputils.h"><violation beginline="31" endline="31" rule="Rule6-6-5" ruleset="Statements">
</violation><violation beginline="65" endline="65" rule="Rule4-10-2" ruleset="Expressions">
</violation><violation beginline="41" endline="41" rule="Rule7-5-4" ruleset="Declarations">
</violation><violation beginline="41" endline="41" rule="Rule7-5-4" ruleset="Declarations">
</violation></file><file path="c:\openxray\externals\bugtrap\source\client\encoding.cpp"><violation beginline="105" endline="105" rule="Rule6-6-5" ruleset="Statements">
</violation><violation beginline="158" endline="158" rule="Rule6-6-5" ruleset="Statements">
</violation><violation beginline="56" endline="56" rule="Rule7-5-4" ruleset="Declarations">
</violation><violation beginline="56" endline="56" rule="Rule7-5-4" ruleset="Declarations">
</violation><violation beginline="251" endline="251" rule="Rule6-6-5" ruleset="Statements">
</violation><violation beginline="290" endline="290" rule="Rule4-10-2" ruleset="Expressions">
</violation><violation beginline="294" endline="294" rule="Rule4-5-2" ruleset="Expressions">
</violation><violation beginline="294" endline="294" rule="Rule4-5-2" ruleset="Expressions">
</violation><violation beginline="295" endline="295" rule="Rule6-6-5" ruleset="Statements">
</violation><violation beginline="351" endline="351" rule="Rule6-6-5" ruleset="Statements">
</violation><violation beginline="410" endline="410" rule="Rule4-10-2" ruleset="Expressions">
</violation><violation beginline="410" endline="410" rule="Rule4-10-2" ruleset="Expressions">
</violation><violation beginline="430" endline="430" rule="Rule6-6-5" ruleset="Statements">
</violation><violation beginline="453" endline="453" rule="Rule4-10-2" ruleset="Expressions">
</violation><violation beginline="453" endline="453" rule="Rule4-10-2" ruleset="Expressions">
</violation><violation beginline="528" endline="528" rule="Rule6-6-5" ruleset="Statements">
</violation><violation beginline="543" endline="543" rule="Rule6-6-5" ruleset="Statements">
</violation><violation beginline="564" endline="564" rule="Rule4-10-2" ruleset="Expressions">
</violation><violation beginline="564" endline="564" rule="Rule4-10-2" ruleset="Expressions">
</violation><violation beginline="601" endline="601" rule="Rule6-6-5" ruleset="Statements">
</violation><violation beginline="633" endline="633" rule="Rule6-6-5" ruleset="Statements">
</violation><violation beginline="650" endline="650" rule="Rule6-6-5" ruleset="Statements">
</violation><violation beginline="56" endline="56" rule="Rule7-5-4" ruleset="Declarations">
</violation><violation beginline="693" endline="693" rule="Rule6-6-5" ruleset="Statements">
</violation><violation beginline="723" endline="723" rule="Rule6-4-4" ruleset="Statements">
</violation><violation beginline="728" endline="728" rule="Rule6-6-5" ruleset="Statements">
</violation><violation beginline="734" endline="734" rule="Rule4-10-2" ruleset="Expressions">
</violation><violation beginline="747" endline="747" rule="Rule6-6-5" ruleset="Statements">
</violation><violation beginline="783" endline="783" rule="Rule6-6-5" ruleset="Statements">
</violation><violation beginline="807" endline="807" rule="Rule6-6-5" ruleset="Statements">
</violation><violation beginline="823" endline="823" rule="Rule5-14-1" ruleset="Statements">
</violation><violation beginline="827" endline="827" rule="Rule6-6-5" ruleset="Statements">
</violation><violation beginline="830" endline="830" rule="Rule5-14-1" ruleset="Statements">
</violation><violation beginline="837" endline="837" rule="Rule5-14-1" ruleset="Statements">
</violation><violation beginline="866" endline="866" rule="Rule6-6-5" ruleset="Statements">
</violation><violation beginline="882" endline="882" rule="Rule6-6-5" ruleset="Statements">
</violation></file><file path="c:\openxray\externals\bugtrap\source\client\encoding.h"><violation beginline="100" endline="100" rule="Rule4-10-2" ruleset="Expressions">
</violation><violation beginline="100" endline="100" rule="Rule4-10-2" ruleset="Expressions">
</violation><violation beginline="114" endline="114" rule="Rule4-10-2" ruleset="Expressions">
</violation><violation beginline="148" endline="148" rule="Rule4-10-2" ruleset="Expressions">
</violation><violation beginline="197" endline="197" rule="Rule4-10-2" ruleset="Expressions">
</violation><violation beginline="220" endline="220" rule="Rule7-5-4" ruleset="Declarations">
</violation><violation beginline="224" endline="224" rule="Rule7-5-4" ruleset="Declarations">
</violation><violation beginline="222" endline="222" rule="Rule7-5-4" ruleset="Declarations">
</violation><violation beginline="226" endline="226" rule="Rule7-5-4" ruleset="Declarations">
</violation><violation beginline="221" endline="221" rule="Rule7-5-4" ruleset="Declarations">
</violation><violation beginline="225" endline="225" rule="Rule7-5-4" ruleset="Declarations">
</violation><violation beginline="223" endline="223" rule="Rule7-5-4" ruleset="Declarations">
</violation><violation beginline="227" endline="227" rule="Rule7-5-4" ruleset="Declarations">
</violation><violation beginline="383" endline="383" rule="Rule4-10-2" ruleset="Expressions">
</violation><violation beginline="401" endline="401" rule="Rule4-10-2" ruleset="Expressions">
</violation><violation beginline="401" endline="401" rule="Rule4-10-2" ruleset="Expressions">
</violation><violation beginline="409" endline="409" rule="Rule7-5-4" ruleset="Declarations">
</violation><violation beginline="355" endline="355" rule="Rule7-5-4" ruleset="Declarations">
</violation><violation beginline="413" endline="413" rule="Rule7-5-4" ruleset="Declarations">
</violation><violation beginline="491" endline="491" rule="Rule4-10-2" ruleset="Expressions">
</violation><violation beginline="491" endline="491" rule="Rule4-10-2" ruleset="Expressions">
</violation><violation beginline="495" endline="495" rule="Rule7-5-4" ruleset="Declarations">
</violation><violation beginline="231" endline="231" rule="Rule7-5-4" ruleset="Declarations">
</violation><violation beginline="222" endline="222" rule="Rule7-5-4" ruleset="Declarations">
</violation><violation beginline="229" endline="229" rule="Rule7-5-4" ruleset="Declarations">
</violation><violation beginline="232" endline="232" rule="Rule7-5-4" ruleset="Declarations">
</violation><violation beginline="268" endline="268" rule="Rule7-5-4" ruleset="Declarations">
</violation><violation beginline="297" endline="297" rule="Rule7-5-4" ruleset="Declarations">
</violation><violation beginline="326" endline="326" rule="Rule7-5-4" ruleset="Declarations">
</violation><violation beginline="355" endline="355" rule="Rule7-5-4" ruleset="Declarations">
</violation><violation beginline="268" endline="268" rule="Rule7-5-4" ruleset="Declarations">
</violation><violation beginline="297" endline="297" rule="Rule7-5-4" ruleset="Declarations">
</violation><violation beginline="355" endline="355" rule="Rule7-5-4" ruleset="Declarations">
</violation><violation beginline="245" endline="245" rule="Rule7-5-4" ruleset="Declarations">
</violation><violation beginline="379" endline="379" rule="Rule7-5-4" ruleset="Declarations">
</violation><violation beginline="385" endline="385" rule="Rule7-5-4" ruleset="Declarations">
</violation><violation beginline="379" endline="379" rule="Rule7-5-4" ruleset="Declarations">
</violation><violation beginline="385" endline="385" rule="Rule7-5-4" ruleset="Declarations">
</violation></file><file path="c:\openxray\externals\bugtrap\source\client\inputstream.h"><violation beginline="28" endline="28" rule="Rule7-5-4" ruleset="Declarations">
</violation><violation beginline="28" endline="28" rule="Rule7-5-4" ruleset="Declarations">
</violation></file><file path="c:\openxray\externals\bugtrap\source\client\memstream.h"><violation beginline="20" endline="20" rule="Rule10-1-1" ruleset="Classes">
</violation></file><file path="c:\openxray\externals\bugtrap\source\client\outputstream.h"><violation beginline="32" endline="32" rule="Rule7-5-4" ruleset="Declarations">
</violation><violation beginline="32" endline="32" rule="Rule7-5-4" ruleset="Declarations">
</violation><violation beginline="30" endline="30" rule="Rule7-5-4" ruleset="Declarations">
</violation><violation beginline="28" endline="28" rule="Rule7-5-4" ruleset="Declarations">
</violation><violation beginline="34" endline="34" rule="Rule7-5-4" ruleset="Declarations">
</violation><violation beginline="28" endline="28" rule="Rule7-5-4" ruleset="Declarations">
</violation><violation beginline="28" endline="28" rule="Rule7-5-4" ruleset="Declarations">
</violation><violation beginline="28" endline="28" rule="Rule7-5-4" ruleset="Declarations">
</violation><violation beginline="28" endline="28" rule="Rule7-5-4" ruleset="Declarations">
</violation><violation beginline="28" endline="28" rule="Rule7-5-4" ruleset="Declarations">
</violation><violation beginline="28" endline="28" rule="Rule7-5-4" ruleset="Declarations">
</violation><violation beginline="28" endline="28" rule="Rule7-5-4" ruleset="Declarations">
</violation><violation beginline="28" endline="28" rule="Rule7-5-4" ruleset="Declarations">
</violation><violation beginline="28" endline="28" rule="Rule7-5-4" ruleset="Declarations">
</violation><violation beginline="28" endline="28" rule="Rule7-5-4" ruleset="Declarations">
</violation><violation beginline="28" endline="28" rule="Rule7-5-4" ruleset="Declarations">
</violation><violation beginline="32" endline="32" rule="Rule7-5-4" ruleset="Declarations">
</violation><violation beginline="32" endline="32" rule="Rule7-5-4" ruleset="Declarations">
</violation></file><file path="c:\openxray\externals\bugtrap\source\client\stream.h"><violation beginline="20" endline="20" rule="Rule10-1-1" ruleset="Classes">
</violation><violation beginline="20" endline="20" rule="Rule10-1-1" ruleset="Classes">
</violation><violation beginline="20" endline="20" rule="Rule10-1-1" ruleset="Classes">
</violation><violation beginline="20" endline="20" rule="Rule10-1-1" ruleset="Classes">
</violation></file><file path="h:\programs\codergears\cppdepend\defaulttoolchain\include\string.h"><violation beginline="83" endline="83" rule="Rule7-5-4" ruleset="Declarations">
</violation><violation beginline="83" endline="83" rule="Rule7-5-4" ruleset="Declarations">
</violation><violation beginline="83" endline="83" rule="Rule7-5-4" ruleset="Declarations">
</violation><violation beginline="72" endline="72" rule="Rule7-5-4" ruleset="Declarations">
</violation><violation beginline="73" endline="73" rule="Rule7-5-4" ruleset="Declarations">
</violation><violation beginline="71" endline="71" rule="Rule7-5-4" ruleset="Declarations">
</violation><violation beginline="71" endline="71" rule="Rule7-5-4" ruleset="Declarations">
</violation><violation beginline="71" endline="71" rule="Rule7-5-4" ruleset="Declarations">
</violation></file><file path="h:\programs\codergears\cppdepend\defaulttoolchain\include\winnls.h"><violation beginline="617" endline="617" rule="Rule7-5-4" ruleset="Declarations">
</violation><violation beginline="624" endline="624" rule="Rule7-5-4" ruleset="Declarations">
</violation><violation beginline="631" endline="631" rule="Rule7-5-4" ruleset="Declarations">
</violation><violation beginline="631" endline="631" rule="Rule7-5-4" ruleset="Declarations">
</violation><violation beginline="617" endline="617" rule="Rule7-5-4" ruleset="Declarations">
</violation><violation beginline="631" endline="631" rule="Rule7-5-4" ruleset="Declarations">
</violation><violation beginline="617" endline="617" rule="Rule7-5-4" ruleset="Declarations">
</violation></file></cppdepend-plugin>