<?xml version="1.0" encoding="UTF-8"?><results version="2">    <cppcheck version="2.1"/>    <errors>        <error id="uninitMemberVar" severity="warning" msg="Member variable &apos;SDebugInfo::x&apos; is not initialized in the constructor." verbose="Member variable &apos;SDebugInfo::x&apos; is not initialized in the constructor." cwe="398">            <location file0="C:\OpenXRay\src\xrGame\ai\monsters\basemonster\base_monster.cpp" file="C:\OpenXRay\src\xrGame\ai\monsters\basemonster\base_monster.h" line="446" column="9"/>            <symbol>SDebugInfo::x</symbol>        </error>        <error id="uninitMemberVar" severity="warning" msg="Member variable &apos;SDebugInfo::y&apos; is not initialized in the constructor." verbose="Member variable &apos;SDebugInfo::y&apos; is not initialized in the constructor." cwe="398">            <location file0="C:\OpenXRay\src\xrGame\ai\monsters\basemonster\base_monster.cpp" file="C:\OpenXRay\src\xrGame\ai\monsters\basemonster\base_monster.h" line="446" column="9"/>            <symbol>SDebugInfo::y</symbol>        </error>        <error id="uninitMemberVar" severity="warning" msg="Member variable &apos;SDebugInfo::delta_y&apos; is not initialized in the constructor." verbose="Member variable &apos;SDebugInfo::delta_y&apos; is not initialized in the constructor." cwe="398">            <location file0="C:\OpenXRay\src\xrGame\ai\monsters\basemonster\base_monster.cpp" file="C:\OpenXRay\src\xrGame\ai\monsters\basemonster\base_monster.h" line="446" column="9"/>            <symbol>SDebugInfo::delta_y</symbol>        </error>        <error id="unusedFunction" severity="style" msg="The function &apos;PHHit&apos; is never used." verbose="The function &apos;PHHit&apos; is never used." cwe="561">            <location file="C:\OpenXRay\src\xrGame\ai\monsters\basemonster\base_monster.cpp" line="457" column="0"/>            <symbol>PHHit</symbol>        </error>        <error id="unusedFunction" severity="style" msg="The function &apos;PlayParticles&apos; is never used." verbose="The function &apos;PlayParticles&apos; is never used." cwe="561">            <location file="C:\OpenXRay\src\xrGame\ai\monsters\basemonster\base_monster.cpp" line="786" column="0"/>            <symbol>PlayParticles</symbol>        </error>        <error id="unusedFunction" severity="style" msg="The function &apos;SetTurnAnimation&apos; is never used." verbose="The function &apos;SetTurnAnimation&apos; is never used." cwe="561">            <location file="C:\OpenXRay\src\xrGame\ai\monsters\basemonster\base_monster.cpp" line="527" column="0"/>            <symbol>SetTurnAnimation</symbol>        </error>        <error id="unusedFunction" severity="style" msg="The function &apos;TranslateActionToPathParams&apos; is never used." verbose="The function &apos;TranslateActionToPathParams&apos; is never used." cwe="561">            <location file="C:\OpenXRay\src\xrGame\ai\monsters\basemonster\base_monster.cpp" line="595" column="0"/>            <symbol>TranslateActionToPathParams</symbol>        </error>        <error id="unusedFunction" severity="style" msg="The function &apos;can_attack_on_move&apos; is never used." verbose="The function &apos;can_attack_on_move&apos; is never used." cwe="561">            <location file="C:\OpenXRay\src\xrGame\ai\monsters\basemonster\base_monster.cpp" line="954" column="0"/>            <symbol>can_attack_on_move</symbol>        </error>        <error id="unusedFunction" severity="style" msg="The function &apos;check_eated_corpse_draggable&apos; is never used." verbose="The function &apos;check_eated_corpse_draggable&apos; is never used." cwe="561">            <location file="C:\OpenXRay\src\xrGame\ai\monsters\basemonster\base_monster.cpp" line="931" column="0"/>            <symbol>check_eated_corpse_draggable</symbol>        </error>        <error id="unusedFunction" severity="style" msg="The function &apos;check_start_conditions&apos; is never used." verbose="The function &apos;check_start_conditions&apos; is never used." cwe="561">            <location file="C:\OpenXRay\src\xrGame\ai\monsters\basemonster\base_monster.cpp" line="842" column="0"/>            <symbol>check_start_conditions</symbol>        </error>        <error id="unusedFunction" severity="style" msg="The function &apos;create_movement_manager&apos; is never used." verbose="The function &apos;create_movement_manager&apos; is never used." cwe="561">            <location file="C:\OpenXRay\src\xrGame\ai\monsters\basemonster\base_monster.cpp" line="721" column="0"/>            <symbol>create_movement_manager</symbol>        </error>        <error id="unusedFunction" severity="style" msg="The function &apos;enemy_accessible&apos; is never used." verbose="The function &apos;enemy_accessible&apos; is never used." cwe="561">            <location file="C:\OpenXRay\src\xrGame\ai\monsters\basemonster\base_monster.cpp" line="255" column="0"/>            <symbol>enemy_accessible</symbol>        </error>        <error id="unusedFunction" severity="style" msg="The function &apos;evaluate&apos; is never used." verbose="The function &apos;evaluate&apos; is never used." cwe="561">            <location file="C:\OpenXRay\src\xrGame\ai\monsters\basemonster\base_monster.cpp" line="500" column="0"/>            <symbol>evaluate</symbol>        </error>        <error id="unusedFunction" severity="style" msg="The function &apos;get_attack_on_move_attack_radius&apos; is never used." verbose="The function &apos;get_attack_on_move_attack_radius&apos; is never used." cwe="561">            <location file="C:\OpenXRay\src\xrGame\ai\monsters\basemonster\base_monster.cpp" line="967" column="0"/>            <symbol>get_attack_on_move_attack_radius</symbol>        </error>        <error id="unusedFunction" severity="style" msg="The function &apos;get_attack_on_move_far_radius&apos; is never used." verbose="The function &apos;get_attack_on_move_far_radius&apos; is never used." cwe="561">            <location file="C:\OpenXRay\src\xrGame\ai\monsters\basemonster\base_monster.cpp" line="960" column="0"/>            <symbol>get_attack_on_move_far_radius</symbol>        </error>        <error id="unusedFunction" severity="style" msg="The function &apos;get_attack_on_move_max_go_close_time&apos; is never used." verbose="The function &apos;get_attack_on_move_max_go_close_time&apos; is never used." cwe="561">            <location file="C:\OpenXRay\src\xrGame\ai\monsters\basemonster\base_monster.cpp" line="955" column="0"/>            <symbol>get_attack_on_move_max_go_close_time</symbol>        </error>        <error id="unusedFunction" severity="style" msg="The function &apos;get_attack_on_move_prediction_factor&apos; is never used." verbose="The function &apos;get_attack_on_move_prediction_factor&apos; is never used." cwe="561">            <location file="C:\OpenXRay\src\xrGame\ai\monsters\basemonster\base_monster.cpp" line="977" column="0"/>            <symbol>get_attack_on_move_prediction_factor</symbol>        </error>        <error id="unusedFunction" severity="style" msg="The function &apos;get_attack_on_move_prepare_radius&apos; is never used." verbose="The function &apos;get_attack_on_move_prepare_radius&apos; is never used." cwe="561">            <location file="C:\OpenXRay\src\xrGame\ai\monsters\basemonster\base_monster.cpp" line="982" column="0"/>            <symbol>get_attack_on_move_prepare_radius</symbol>        </error>        <error id="unusedFunction" severity="style" msg="The function &apos;get_attack_on_move_prepare_time&apos; is never used." verbose="The function &apos;get_attack_on_move_prepare_time&apos; is never used." cwe="561">            <location file="C:\OpenXRay\src\xrGame\ai\monsters\basemonster\base_monster.cpp" line="987" column="0"/>            <symbol>get_attack_on_move_prepare_time</symbol>        </error>        <error id="unusedFunction" severity="style" msg="The function &apos;get_attack_on_move_update_side_period&apos; is never used." verbose="The function &apos;get_attack_on_move_update_side_period&apos; is never used." cwe="561">            <location file="C:\OpenXRay\src\xrGame\ai\monsters\basemonster\base_monster.cpp" line="972" column="0"/>            <symbol>get_attack_on_move_update_side_period</symbol>        </error>        <error id="unusedFunction" severity="style" msg="The function &apos;get_attack_rebuild_time&apos; is never used." verbose="The function &apos;get_attack_rebuild_time&apos; is never used." cwe="561">            <location file="C:\OpenXRay\src\xrGame\ai\monsters\basemonster\base_monster.cpp" line="701" column="0"/>            <symbol>get_attack_rebuild_time</symbol>        </error>        <error id="unusedFunction" severity="style" msg="The function &apos;get_fire_influence&apos; is never used." verbose="The function &apos;get_fire_influence&apos; is never used." cwe="561">            <location file="C:\OpenXRay\src\xrGame\ai\monsters\basemonster\base_monster.cpp" line="994" column="0"/>            <symbol>get_fire_influence</symbol>        </error>        <error id="unusedFunction" severity="style" msg="The function &apos;get_psy_influence&apos; is never used." verbose="The function &apos;get_psy_influence&apos; is never used." cwe="561">            <location file="C:\OpenXRay\src\xrGame\ai\monsters\basemonster\base_monster.cpp" line="992" column="0"/>            <symbol>get_psy_influence</symbol>        </error>        <error id="unusedFunction" severity="style" msg="The function &apos;get_radiation_influence&apos; is never used." verbose="The function &apos;get_radiation_influence&apos; is never used." cwe="561">            <location file="C:\OpenXRay\src\xrGame\ai\monsters\basemonster\base_monster.cpp" line="993" column="0"/>            <symbol>get_radiation_influence</symbol>        </error>        <error id="unusedFunction" severity="style" msg="The function &apos;load_effector&apos; is never used." verbose="The function &apos;load_effector&apos; is never used." cwe="561">            <location file="C:\OpenXRay\src\xrGame\ai\monsters\basemonster\base_monster.cpp" line="813" column="0"/>            <symbol>load_effector</symbol>        </error>        <error id="unusedFunction" severity="style" msg="The function &apos;ph_destroyable&apos; is never used." verbose="The function &apos;ph_destroyable&apos; is never used." cwe="561">            <location file="C:\OpenXRay\src\xrGame\ai\monsters\basemonster\base_monster.cpp" line="458" column="0"/>            <symbol>ph_destroyable</symbol>        </error>        <error id="unusedFunction" severity="style" msg="The function &apos;set_action&apos; is never used." verbose="The function &apos;set_action&apos; is never used." cwe="561">            <location file="C:\OpenXRay\src\xrGame\ai\monsters\basemonster\base_monster.cpp" line="785" column="0"/>            <symbol>set_action</symbol>        </error>        <error id="unusedFunction" severity="style" msg="The function &apos;set_state_sound&apos; is never used." verbose="The function &apos;set_state_sound&apos; is never used." cwe="561">            <location file="C:\OpenXRay\src\xrGame\ai\monsters\basemonster\base_monster.cpp" line="532" column="0"/>            <symbol>set_state_sound</symbol>        </error>        <error id="unusedFunction" severity="style" msg="The function &apos;useful&apos; is never used." verbose="The function &apos;useful&apos; is never used." cwe="561">            <location file="C:\OpenXRay\src\xrGame\ai\monsters\basemonster\base_monster.cpp" line="459" column="0"/>            <symbol>useful</symbol>        </error>        <error id="unmatchedSuppression" severity="information" msg="Unmatched suppression: missingIncludeSystem" verbose="Unmatched suppression: missingIncludeSystem"/>        <error id="unmatchedSuppression" severity="information" msg="Unmatched suppression: preprocessorErrorDirective" verbose="Unmatched suppression: preprocessorErrorDirective"/>        <error id="unmatchedSuppression" severity="information" msg="Unmatched suppression: unknownMacro" verbose="Unmatched suppression: unknownMacro"/>        <error id="missingInclude" severity="information" msg="Cppcheck cannot find all the include files (use --check-config for details)" verbose="Cppcheck cannot find all the include files. Cppcheck can check the code without the include files found. But the results will probably be more accurate if all the include files are found. Please check your project&apos;s include directories and add all of them as include directories for Cppcheck. To see what files Cppcheck cannot find use --check-config."/>    </errors></results>