<?xml version="1.0" encoding="UTF-8"?>
<cppdepend-plugin tool="Misra">
<file path="c:\openxray\externals\luabind\luabind\class.hpp"><violation beginline="178" endline="178" rule="Rule4-10-2" ruleset="Expressions">
</violation><violation beginline="232" endline="232" rule="Rule11-0-1" ruleset="Classes">
</violation><violation beginline="266" endline="266" rule="Rule11-0-1" ruleset="Classes">
</violation><violation beginline="315" endline="315" rule="Rule5-14-1" ruleset="Statements">
</violation><violation beginline="320" endline="320" rule="Rule5-14-1" ruleset="Statements">
</violation><violation beginline="334" endline="334" rule="Rule11-0-1" ruleset="Classes">
</violation><violation beginline="409" endline="409" rule="Rule11-0-1" ruleset="Classes">
</violation><violation beginline="508" endline="508" rule="Rule7-5-4" ruleset="Declarations">
</violation><violation beginline="238" endline="238" rule="Rule7-5-4" ruleset="Declarations">
</violation><violation beginline="545" endline="545" rule="Rule7-5-4" ruleset="Declarations">
</violation><violation beginline="252" endline="252" rule="Rule7-5-4" ruleset="Declarations">
</violation><violation beginline="242" endline="242" rule="Rule7-5-4" ruleset="Declarations">
</violation><violation beginline="252" endline="252" rule="Rule7-5-4" ruleset="Declarations">
</violation><violation beginline="252" endline="252" rule="Rule7-5-4" ruleset="Declarations">
</violation></file><file path="c:\openxray\externals\luabind\luabind\class_info.hpp"><violation beginline="33" endline="33" rule="Rule11-0-1" ruleset="Classes">
</violation><violation beginline="33" endline="33" rule="Rule11-0-1" ruleset="Classes">
</violation></file><file path="c:\openxray\externals\luabind\luabind\detail\class_registry.hpp"><violation beginline="42" endline="42" rule="Rule7-5-4" ruleset="Declarations">
</violation><violation beginline="55" endline="55" rule="Rule7-5-4" ruleset="Declarations">
</violation></file><file path="c:\openxray\externals\luabind\luabind\detail\class_rep.hpp"><violation beginline="211" endline="211" rule="Rule7-5-4" ruleset="Declarations">
</violation><violation beginline="121" endline="121" rule="Rule7-5-4" ruleset="Declarations">
</violation><violation beginline="116" endline="116" rule="Rule7-5-4" ruleset="Declarations">
</violation></file><file path="c:\openxray\externals\luabind\luabind\detail\enum_maker.hpp"><violation beginline="91" endline="91" rule="Rule11-0-1" ruleset="Classes">
</violation></file><file path="c:\openxray\externals\luabind\luabind\detail\format_signature.hpp"><violation beginline="29" endline="29" rule="Rule7-5-4" ruleset="Declarations">
</violation></file><file path="c:\openxray\externals\luabind\luabind\detail\link_compatibility.hpp"><violation beginline="43" endline="43" rule="Rule7-5-4" ruleset="Declarations">
</violation></file><file path="c:\openxray\externals\luabind\luabind\detail\object.hpp"><violation beginline="49" endline="49" rule="Rule7-5-4" ruleset="Declarations">
</violation><violation beginline="225" endline="225" rule="Rule7-5-4" ruleset="Declarations">
</violation><violation beginline="49" endline="49" rule="Rule7-5-4" ruleset="Declarations">
</violation><violation beginline="225" endline="225" rule="Rule7-5-4" ruleset="Declarations">
</violation><violation beginline="49" endline="49" rule="Rule7-5-4" ruleset="Declarations">
</violation><violation beginline="225" endline="225" rule="Rule7-5-4" ruleset="Declarations">
</violation><violation beginline="49" endline="49" rule="Rule7-5-4" ruleset="Declarations">
</violation><violation beginline="225" endline="225" rule="Rule7-5-4" ruleset="Declarations">
</violation><violation beginline="225" endline="225" rule="Rule7-5-4" ruleset="Declarations">
</violation></file><file path="c:\openxray\externals\luabind\luabind\detail\object_rep.hpp"><violation beginline="128" endline="128" rule="Rule7-5-4" ruleset="Declarations">
</violation><violation beginline="49" endline="49" rule="Rule7-5-4" ruleset="Declarations">
</violation></file><file path="c:\openxray\externals\luabind\luabind\detail\property.hpp"><violation beginline="12" endline="12" rule="Rule11-0-1" ruleset="Classes">
</violation></file><file path="c:\openxray\externals\luabind\luabind\from_stack.hpp"><violation beginline="30" endline="30" rule="Rule11-0-1" ruleset="Classes">
</violation></file><file path="c:\openxray\externals\luabind\luabind\lua_argument_proxy.hpp"><violation beginline="33" endline="33" rule="Rule7-5-4" ruleset="Declarations">
</violation><violation beginline="28" endline="28" rule="Rule7-5-4" ruleset="Declarations">
</violation></file><file path="c:\openxray\externals\luabind\luabind\make_function.hpp"><violation beginline="96" endline="96" rule="Rule7-5-4" ruleset="Declarations">
</violation></file><file path="c:\openxray\externals\luabind\luabind\memory.hpp"><violation beginline="27" endline="27" rule="Rule7-5-4" ruleset="Declarations">
</violation><violation beginline="27" endline="27" rule="Rule7-5-4" ruleset="Declarations">
</violation><violation beginline="27" endline="27" rule="Rule7-5-4" ruleset="Declarations">
</violation><violation beginline="27" endline="27" rule="Rule7-5-4" ruleset="Declarations">
</violation></file><file path="c:\openxray\externals\luabind\luabind\memory_allocator.hpp"><violation beginline="48" endline="48" rule="Rule4-10-2" ruleset="Expressions">
</violation><violation beginline="144" endline="144" rule="Rule6-6-5" ruleset="Statements">
</violation></file><file path="c:\openxray\externals\luabind\src\class_info.cpp"><violation beginline="44" endline="44" rule="Rule4-10-2" ruleset="Expressions">
</violation><violation beginline="104" endline="104" rule="Rule6-6-5" ruleset="Statements">
</violation></file><file path="h:\programs\codergears\cppdepend\defaulttoolchain\compiler\include\c++\bits\stl_pair.h"><violation beginline="198" endline="198" rule="Rule11-0-1" ruleset="Classes">
</violation></file><file path="h:\programs\codergears\cppdepend\defaulttoolchain\compiler\include\c++\bits\stl_tree.h"><violation beginline="326" endline="326" rule="Rule11-0-1" ruleset="Classes">
</violation></file></cppdepend-plugin>