<?xml version="1.0" encoding="UTF-8"?>
<cppdepend-plugin tool="Misra">
<file path="c:\openxray\externals\ode\include\ode\mass.h"><violation beginline="74" endline="74" rule="Rule11-0-1" ruleset="Classes">
</violation><violation beginline="36" endline="36" rule="Rule7-5-4" ruleset="Declarations">
</violation><violation beginline="36" endline="36" rule="Rule7-5-4" ruleset="Declarations">
</violation><violation beginline="65" endline="65" rule="Rule7-5-4" ruleset="Declarations">
</violation><violation beginline="67" endline="67" rule="Rule7-5-4" ruleset="Declarations">
</violation></file><file path="c:\openxray\externals\ode\include\ode\odemath.h"><violation beginline="222" endline="222" rule="Rule7-5-4" ruleset="Declarations">
</violation></file><file path="c:\openxray\externals\ode\ode\src\mass.cpp"><violation beginline="44" endline="44" rule="Rule6-6-5" ruleset="Statements">
</violation><violation beginline="34" endline="34" rule="Rule7-5-4" ruleset="Declarations">
</violation><violation beginline="312" endline="312" rule="Rule6-3-1" ruleset="Statements">
</violation></file></cppdepend-plugin>