<Root>
<Comments/>
<Macros/>
<Comments>
<c f="1" b="1" e="21"/>
<c f="1" b="23" e="23"/>
<c f="1" b="24" e="24"/>
<c f="1" b="26" e="0"/>
<c f="1" b="33" e="33"/>
<c f="1" b="34" e="0"/>
<c f="1" b="34" e="34"/>
<c f="1" b="36" e="0"/>
<c f="1" b="37" e="37"/>
<c f="1" b="38" e="0"/>
<c f="1" b="38" e="38"/>
<c f="1" b="39" e="0"/>
<c f="1" b="39" e="39"/>
<c f="1" b="40" e="0"/>
<c f="1" b="40" e="40"/>
<c f="1" b="41" e="41"/>
<c f="1" b="42" e="0"/>
<c f="1" b="43" e="43"/>
<c f="1" b="45" e="45"/>
<c f="1" b="46" e="0"/>
<c f="1" b="46" e="46"/>
<c f="1" b="47" e="0"/>
<c f="1" b="47" e="47"/>
<c f="1" b="48" e="0"/>
<c f="1" b="48" e="48"/>
<c f="1" b="49" e="0"/>
<c f="1" b="49" e="49"/>
<c f="1" b="50" e="50"/>
<c f="1" b="51" e="51"/>
<c f="1" b="52" e="0"/>
<c f="1" b="54" e="54"/>
<c f="1" b="55" e="0"/>
<c f="1" b="62" e="62"/>
<c f="1" b="63" e="0"/>
</Comments>
<Macros>
<m f="1" bl="66" bc="52" el="66" ec="52"/>
</Macros>
<tun>
<cr access="public" depth="0" kind="class" name="dMatrix" id="7479261a19d8caf3e9083b64a7fc171e_f9c1595ee35ee1df778e88e7e865635a" file="1" linestart="32" lineend="68">
<cr access="public" kind="class" name="dMatrix" id="7479261a19d8caf3e9083b64a7fc171e_c97e475563b3e1fadc719e957df1ab28" file="1" linestart="32" lineend="32"/>
<fl name="n" id="7479261a19d8caf3e9083b64a7fc171e_44c90156e6d3be3a5384b958814ba9f0" file="1" linestart="33" lineend="33" isLiteral="true" access="private" proto="int">
<bt name="int"/>
</fl>
<fl name="m" id="7479261a19d8caf3e9083b64a7fc171e_55d1164524980f21336331fffd4e97be" file="1" linestart="33" lineend="33" isLiteral="true" access="private" proto="int">
<bt name="int"/>
</fl>
<fl name="data" id="7479261a19d8caf3e9083b64a7fc171e_bad72b374ebef83e0808bbde8d15a1a4" file="1" linestart="34" lineend="34" isPtr="true" isLiteral="true" access="private" proto="int *">
<pt>
<bt name="int"/>
</pt>
</fl>
<asd access="public"/>
<c name="dMatrix" id="7479261a19d8caf3e9083b64a7fc171e_3bd5cbf63af18dd293687ece8ff28f98" file="1" linestart="38" lineend="38" access="public" hasbody="true">
<fpt cc="cdecl" proto="void">
<bt name="void"/>
</fpt>
</c>
<c name="dMatrix" id="7479261a19d8caf3e9083b64a7fc171e_d0e33bd2230dffede970a6ddd07d4164" file="1" linestart="39" lineend="39" access="public" hasbody="true">
<fpt cc="cdecl" proto="void">
<bt name="void"/>
</fpt>
<p name="rows" proto="int" isLiteral="true" isPrimitive="true" access2="none">
<bt name="int"/>
<Stmt>

</Stmt>
</p>
<p name="cols" proto="int" isLiteral="true" isPrimitive="true" access2="none">
<bt name="int"/>
<Stmt>

</Stmt>
</p>
</c>
<c name="dMatrix" id="7479261a19d8caf3e9083b64a7fc171e_ba777c7a74e7632087eba300793e6c0e" file="1" linestart="40" lineend="40" copyconst="true" access="public" hasbody="true">
<fpt cc="cdecl" proto="void">
<bt name="void"/>
</fpt>
<p name="" proto="const dMatrix &amp;" isRef="true" isLiteral="true" access2="none">
<lrf>
<QualType const="true">
<rt>
<cr id="7479261a19d8caf3e9083b64a7fc171e_f9c1595ee35ee1df778e88e7e865635a"/>
</rt>
</QualType>
</lrf>
<Stmt>

</Stmt>
</p>
</c>
<c name="dMatrix" id="7479261a19d8caf3e9083b64a7fc171e_49dc5f98daecf42305a9a8c61eb21cda" file="1" linestart="42" lineend="42" access="public">
<fpt cc="cdecl" proto="void">
<bt name="void"/>
</fpt>
<p name="rows" proto="int" isLiteral="true" isPrimitive="true" access2="none">
<bt name="int"/>
<Stmt>

</Stmt>
</p>
<p name="cols" proto="int" isLiteral="true" isPrimitive="true" access2="none">
<bt name="int"/>
<Stmt>

</Stmt>
</p>
<p name="_data" proto="int *" isPtr="true" isLiteral="true" access2="none">
<pt>
<bt name="int"/>
</pt>
<Stmt>

</Stmt>
</p>
<p name="rowskip" proto="int" isLiteral="true" isPrimitive="true" access2="none">
<bt name="int"/>
<Stmt>

</Stmt>
</p>
<p name="colskip" proto="int" isLiteral="true" isPrimitive="true" access2="none">
<bt name="int"/>
<Stmt>

</Stmt>
</p>
</c>
<d name="~dMatrix" id="7479261a19d8caf3e9083b64a7fc171e_71629d37f73b3c6cfc5199b39dd7f4b8" file="1" linestart="43" lineend="43" access="public" hasbody="true">
<fpt cc="cdecl" proto="void">
<bt name="void"/>
</fpt>
</d>
<m name="operator()" id="7479261a19d8caf3e9083b64a7fc171e_cf79f80319363a0aaf4c233873cbed40" file="1" linestart="46" lineend="46" operator="true" access="public">
<fpt cc="cdecl" proto="int &amp;">
<lrf>
<bt name="int"/>
</lrf>
</fpt>
<p name="i" proto="int" isLiteral="true" isPrimitive="true" access2="none">
<bt name="int"/>
<Stmt>

</Stmt>
</p>
<p name="j" proto="int" isLiteral="true" isPrimitive="true" access2="none">
<bt name="int"/>
<Stmt>

</Stmt>
</p>
</m>
<m name="operator=" id="7479261a19d8caf3e9083b64a7fc171e_347d348c596d16733bed75f82e4ea9ee" file="1" linestart="47" lineend="47" operator="true" access="public" hasbody="true">
<fpt cc="cdecl" proto="void">
<bt name="void"/>
</fpt>
<p name="" proto="const dMatrix &amp;" isRef="true" isLiteral="true" access2="none">
<lrf>
<QualType const="true">
<rt>
<cr id="7479261a19d8caf3e9083b64a7fc171e_f9c1595ee35ee1df778e88e7e865635a"/>
</rt>
</QualType>
</lrf>
<Stmt>

</Stmt>
</p>
</m>
<m name="operator=" id="7479261a19d8caf3e9083b64a7fc171e_89717ef31692fc7e158ce0000e45b73a" file="1" linestart="48" lineend="48" operator="true" access="public">
<fpt cc="cdecl" proto="void">
<bt name="void"/>
</fpt>
<p name="" proto="int" isLiteral="true" isPrimitive="true" access2="none">
<bt name="int"/>
<Stmt>

</Stmt>
</p>
</m>
<m name="transpose" id="7479261a19d8caf3e9083b64a7fc171e_e9fb51c814a87360d25726b34bfa1a2e" file="1" linestart="49" lineend="49" access="public" hasbody="true">
<fpt cc="cdecl" proto="dMatrix">
<rt>
<cr id="7479261a19d8caf3e9083b64a7fc171e_f9c1595ee35ee1df778e88e7e865635a"/>
</rt>
</fpt>
</m>
<m name="select" id="7479261a19d8caf3e9083b64a7fc171e_0043727f9043270345626b4a132e0b84" file="1" linestart="52" lineend="52" access="public" hasbody="true">
<fpt cc="cdecl" proto="dMatrix">
<rt>
<cr id="7479261a19d8caf3e9083b64a7fc171e_f9c1595ee35ee1df778e88e7e865635a"/>
</rt>
</fpt>
<p name="np" proto="int" isLiteral="true" isPrimitive="true" access2="none">
<bt name="int"/>
<Stmt>

</Stmt>
</p>
<p name="p" proto="int *" isPtr="true" isLiteral="true" access2="none">
<pt>
<bt name="int"/>
</pt>
<Stmt>

</Stmt>
</p>
<p name="nq" proto="int" isLiteral="true" isPrimitive="true" access2="none">
<bt name="int"/>
<Stmt>

</Stmt>
</p>
<p name="q" proto="int *" isPtr="true" isLiteral="true" access2="none">
<pt>
<bt name="int"/>
</pt>
<Stmt>

</Stmt>
</p>
</m>
<m name="operator+" id="7479261a19d8caf3e9083b64a7fc171e_b4558ac2716bb7c264e45ebfea551cb6" file="1" linestart="55" lineend="55" operator="true" access="public" hasbody="true">
<fpt cc="cdecl" proto="dMatrix">
<rt>
<cr id="7479261a19d8caf3e9083b64a7fc171e_f9c1595ee35ee1df778e88e7e865635a"/>
</rt>
</fpt>
<p name="" proto="const dMatrix &amp;" isRef="true" isLiteral="true" access2="none">
<lrf>
<QualType const="true">
<rt>
<cr id="7479261a19d8caf3e9083b64a7fc171e_f9c1595ee35ee1df778e88e7e865635a"/>
</rt>
</QualType>
</lrf>
<Stmt>

</Stmt>
</p>
</m>
<m name="operator-" id="7479261a19d8caf3e9083b64a7fc171e_6ebb7f263b8afc24fdebc7e3867ae585" file="1" linestart="56" lineend="56" operator="true" access="public" hasbody="true">
<fpt cc="cdecl" proto="dMatrix">
<rt>
<cr id="7479261a19d8caf3e9083b64a7fc171e_f9c1595ee35ee1df778e88e7e865635a"/>
</rt>
</fpt>
<p name="" proto="const dMatrix &amp;" isRef="true" isLiteral="true" access2="none">
<lrf>
<QualType const="true">
<rt>
<cr id="7479261a19d8caf3e9083b64a7fc171e_f9c1595ee35ee1df778e88e7e865635a"/>
</rt>
</QualType>
</lrf>
<Stmt>

</Stmt>
</p>
</m>
<m name="operator-" id="7479261a19d8caf3e9083b64a7fc171e_b2dcc0631f6276797150f2772bf2099f" file="1" linestart="57" lineend="57" operator="true" access="public" hasbody="true">
<fpt cc="cdecl" proto="dMatrix">
<rt>
<cr id="7479261a19d8caf3e9083b64a7fc171e_f9c1595ee35ee1df778e88e7e865635a"/>
</rt>
</fpt>
</m>
<m name="operator*" id="7479261a19d8caf3e9083b64a7fc171e_0deb58f2e8e47300aef244c0fdbcfc09" file="1" linestart="58" lineend="58" operator="true" access="public" hasbody="true">
<fpt cc="cdecl" proto="dMatrix">
<rt>
<cr id="7479261a19d8caf3e9083b64a7fc171e_f9c1595ee35ee1df778e88e7e865635a"/>
</rt>
</fpt>
<p name="" proto="const dMatrix &amp;" isRef="true" isLiteral="true" access2="none">
<lrf>
<QualType const="true">
<rt>
<cr id="7479261a19d8caf3e9083b64a7fc171e_f9c1595ee35ee1df778e88e7e865635a"/>
</rt>
</QualType>
</lrf>
<Stmt>

</Stmt>
</p>
</m>
<m name="operator+=" id="7479261a19d8caf3e9083b64a7fc171e_03c3e61b81a3281d061f94cc78cfd0c1" file="1" linestart="59" lineend="59" operator="true" access="public" hasbody="true">
<fpt cc="cdecl" proto="void">
<bt name="void"/>
</fpt>
<p name="" proto="const dMatrix &amp;" isRef="true" isLiteral="true" access2="none">
<lrf>
<QualType const="true">
<rt>
<cr id="7479261a19d8caf3e9083b64a7fc171e_f9c1595ee35ee1df778e88e7e865635a"/>
</rt>
</QualType>
</lrf>
<Stmt>

</Stmt>
</p>
</m>
<m name="operator-=" id="7479261a19d8caf3e9083b64a7fc171e_4b1c9727a8e58d2c1a95377ac7d43b7e" file="1" linestart="60" lineend="60" operator="true" access="public" hasbody="true">
<fpt cc="cdecl" proto="void">
<bt name="void"/>
</fpt>
<p name="" proto="const dMatrix &amp;" isRef="true" isLiteral="true" access2="none">
<lrf>
<QualType const="true">
<rt>
<cr id="7479261a19d8caf3e9083b64a7fc171e_f9c1595ee35ee1df778e88e7e865635a"/>
</rt>
</QualType>
</lrf>
<Stmt>

</Stmt>
</p>
</m>
<m name="clearUpperTriangle" id="7479261a19d8caf3e9083b64a7fc171e_86138a2690ba66e5adb6983d55effff7" file="1" linestart="63" lineend="63" access="public" hasbody="true">
<fpt cc="cdecl" proto="void">
<bt name="void"/>
</fpt>
</m>
<m name="clearLowerTriangle" id="7479261a19d8caf3e9083b64a7fc171e_a1bf0d41960cf3ee1a4c899cfb1a981d" file="1" linestart="64" lineend="64" access="public" hasbody="true">
<fpt cc="cdecl" proto="void">
<bt name="void"/>
</fpt>
</m>
<m name="makeRandom" id="7479261a19d8caf3e9083b64a7fc171e_0d06d8d119cd8c3de45af699c18331d4" file="1" linestart="65" lineend="65" access="public">
<fpt cc="cdecl" proto="void">
<bt name="void"/>
</fpt>
<p name="range" proto="int" isLiteral="true" isPrimitive="true" access2="none">
<bt name="int"/>
<Stmt>

</Stmt>
</p>
</m>
<m name="print" id="7479261a19d8caf3e9083b64a7fc171e_7a46d278bff5bc23325cc8e10fd40e8d" file="1" linestart="66" lineend="66" access="public" hasbody="true">
<fpt cc="cdecl" proto="void">
<bt name="void"/>
</fpt>
<p name="fmt" proto="const char *" isPtr="true" isLiteral="true" init="true" access2="none">
<pt>
<QualType const="true">
<bt name="char"/>
</QualType>
</pt>
<Stmt>
<n32 lb="66" cb="33">
<n52 lb="66" cb="33">
<slit/>
</n52>
</n32>

</Stmt>
</p>
<p name="f" proto="FILE *" isPtr="true" isLiteral="true" init="true" access2="none">
<pt>
<Tdef>
<ety>
<rt>
<cr id="551d34c4201f45e199ffddc38791c29c_9b75e14604360f7936837e5997e12eba"/>
</rt>
</ety>
</Tdef>
</pt>
<Stmt>
<n46 lb="66" cb="52" le="66" ce="52">
<exp pvirg="true"/>
<uo lb="66" cb="52" le="66" ce="52" kind="&amp;">
<n2 lb="66" cb="52" le="66" ce="52">
<exp pvirg="true"/>
<n32 lb="66" cb="52">
<drx lb="66" cb="52" kind="lvalue" id="551d34c4201f45e199ffddc38791c29c_9ae2eabed9862d8d1fb4bba66f2f2197" nm="_iob"/>
</n32>
<n45 lb="66" cb="52">
<flit/>
</n45>
</n2>
</uo>
</n46>

</Stmt>
</p>
</m>
<m name="maxDifference" id="7479261a19d8caf3e9083b64a7fc171e_18fad9f1f540cb8a0033a82e6088c375" file="1" linestart="67" lineend="67" access="public">
<fpt cc="cdecl" proto="int">
<bt name="int"/>
</fpt>
<p name="" proto="const dMatrix &amp;" isRef="true" isLiteral="true" access2="none">
<lrf>
<QualType const="true">
<rt>
<cr id="7479261a19d8caf3e9083b64a7fc171e_f9c1595ee35ee1df778e88e7e865635a"/>
</rt>
</QualType>
</lrf>
<Stmt>

</Stmt>
</p>
</m>
</cr>
<c name="dMatrix" id="fa7b08882ecc2022f1b72573ed8765f8_3bd5cbf63af18dd293687ece8ff28f98" file="2" linestart="31" lineend="36" previous="7479261a19d8caf3e9083b64a7fc171e_3bd5cbf63af18dd293687ece8ff28f98" access="public" hasbody="true" isdef="true">
<fpt cc="cdecl" proto="void">
<bt name="void"/>
</fpt>
<Stmt>
<u lb="32" cb="1" le="36" ce="1">
<xop lb="33" cb="3" le="33" ce="7" kind="=">
<mex lb="33" cb="3" kind="lvalue" id="7479261a19d8caf3e9083b64a7fc171e_44c90156e6d3be3a5384b958814ba9f0" nm="n" arrow="1">
<n19 lb="33" cb="3"/>
</mex>
<n45 lb="33" cb="7">
<flit/>
</n45>
</xop>
<xop lb="34" cb="3" le="34" ce="7" kind="=">
<mex lb="34" cb="3" kind="lvalue" id="7479261a19d8caf3e9083b64a7fc171e_55d1164524980f21336331fffd4e97be" nm="m" arrow="1">
<n19 lb="34" cb="3"/>
</mex>
<n45 lb="34" cb="7"/>
</xop>
</u>

</Stmt>
</c>
<c name="dMatrix" id="fa7b08882ecc2022f1b72573ed8765f8_d0e33bd2230dffede970a6ddd07d4164" file="2" linestart="39" lineend="46" previous="7479261a19d8caf3e9083b64a7fc171e_d0e33bd2230dffede970a6ddd07d4164" access="public" hasbody="true" isdef="true">
<fpt cc="cdecl" proto="void">
<bt name="void"/>
</fpt>
<p name="rows" proto="int" isLiteral="true" isPrimitive="true" access2="none">
<bt name="int"/>
<Stmt>

</Stmt>
</p>
<p name="cols" proto="int" isLiteral="true" isPrimitive="true" access2="none">
<bt name="int"/>
<Stmt>

</Stmt>
</p>
<Stmt>
<u lb="40" cb="1" le="46" ce="1">
<if lb="41" cb="3" le="41" ce="56">
<xop lb="41" cb="7" le="41" ce="26" kind="||">
<xop lb="41" cb="7" le="41" ce="14" kind="&lt;">
<n32 lb="41" cb="7">
<drx lb="41" cb="7" kind="lvalue" nm="rows"/>
</n32>
<n45 lb="41" cb="14">
<flit/>
</n45>
</xop>
<xop lb="41" cb="19" le="41" ce="26" kind="&lt;">
<n32 lb="41" cb="19">
<drx lb="41" cb="19" kind="lvalue" nm="cols"/>
</n32>
<n45 lb="41" cb="26"/>
</xop>
</xop>
<ce lb="41" cb="29" le="41" ce="56" nbparm="2" id="bf0a0e7d30c19718305066569bf60630_4bdfc08d4302b7e3823b171d5880f65e">
<exp pvirg="true"/>
<n32 lb="41" cb="29">
<drx lb="41" cb="29" kind="lvalue" id="bf0a0e7d30c19718305066569bf60630_4bdfc08d4302b7e3823b171d5880f65e" nm="dDebug"/>
</n32>
<n45 lb="41" cb="37">
<flit/>
</n45>
<n32 lb="41" cb="39">
<n52 lb="41" cb="39">
<slit/>
</n52>
</n32>
</ce>
</if>
<xop lb="42" cb="3" le="42" ce="7" kind="=">
<mex lb="42" cb="3" kind="lvalue" id="7479261a19d8caf3e9083b64a7fc171e_44c90156e6d3be3a5384b958814ba9f0" nm="n" arrow="1">
<n19 lb="42" cb="3"/>
</mex>
<n32 lb="42" cb="7">
<drx lb="42" cb="7" kind="lvalue" nm="rows"/>
</n32>
</xop>
<xop lb="43" cb="3" le="43" ce="7" kind="=">
<mex lb="43" cb="3" kind="lvalue" id="7479261a19d8caf3e9083b64a7fc171e_55d1164524980f21336331fffd4e97be" nm="m" arrow="1">
<n19 lb="43" cb="3"/>
</mex>
<n32 lb="43" cb="7">
<drx lb="43" cb="7" kind="lvalue" nm="cols"/>
</n32>
</xop>
</u>

</Stmt>
</c>
<c name="dMatrix" id="fa7b08882ecc2022f1b72573ed8765f8_ba777c7a74e7632087eba300793e6c0e" file="2" linestart="49" lineend="55" previous="7479261a19d8caf3e9083b64a7fc171e_ba777c7a74e7632087eba300793e6c0e" copyconst="true" access="public" hasbody="true" isdef="true">
<fpt cc="cdecl" proto="void">
<bt name="void"/>
</fpt>
<p name="a" proto="const dMatrix &amp;" isRef="true" isLiteral="true" access2="none">
<lrf>
<QualType const="true">
<rt>
<cr id="7479261a19d8caf3e9083b64a7fc171e_f9c1595ee35ee1df778e88e7e865635a"/>
</rt>
</QualType>
</lrf>
<Stmt>

</Stmt>
</p>
<Stmt>
<u lb="50" cb="1" le="55" ce="1">
<xop lb="51" cb="3" le="51" ce="9" kind="=">
<mex lb="51" cb="3" kind="lvalue" id="7479261a19d8caf3e9083b64a7fc171e_44c90156e6d3be3a5384b958814ba9f0" nm="n" arrow="1">
<n19 lb="51" cb="3"/>
</mex>
<n32 lb="51" cb="7" le="51" ce="9">
<mex lb="51" cb="7" le="51" ce="9" kind="lvalue" id="7479261a19d8caf3e9083b64a7fc171e_44c90156e6d3be3a5384b958814ba9f0" nm="n" point="1">
<drx lb="51" cb="7" kind="lvalue" nm="a"/>
</mex>
</n32>
</xop>
<xop lb="52" cb="3" le="52" ce="9" kind="=">
<mex lb="52" cb="3" kind="lvalue" id="7479261a19d8caf3e9083b64a7fc171e_55d1164524980f21336331fffd4e97be" nm="m" arrow="1">
<n19 lb="52" cb="3"/>
</mex>
<n32 lb="52" cb="7" le="52" ce="9">
<mex lb="52" cb="7" le="52" ce="9" kind="lvalue" id="7479261a19d8caf3e9083b64a7fc171e_55d1164524980f21336331fffd4e97be" nm="m" point="1">
<drx lb="52" cb="7" kind="lvalue" nm="a"/>
</mex>
</n32>
</xop>
</u>

</Stmt>
</c>
<c name="dMatrix" id="fa7b08882ecc2022f1b72573ed8765f8_49dc5f98daecf42305a9a8c61eb21cda" file="2" linestart="58" lineend="68" access="public" hasbody="true" isdef="true">
<fpt cc="cdecl" proto="void">
<bt name="void"/>
</fpt>
<p name="rows" proto="int" isLiteral="true" isPrimitive="true" access2="none">
<bt name="int"/>
<Stmt>

</Stmt>
</p>
<p name="cols" proto="int" isLiteral="true" isPrimitive="true" access2="none">
<bt name="int"/>
<Stmt>

</Stmt>
</p>
<p name="_data" proto="int *" isPtr="true" isLiteral="true" access2="none">
<pt>
<bt name="int"/>
</pt>
<Stmt>

</Stmt>
</p>
<p name="rowskip" proto="int" isLiteral="true" isPrimitive="true" access2="none">
<bt name="int"/>
<Stmt>

</Stmt>
</p>
<p name="colskip" proto="int" isLiteral="true" isPrimitive="true" access2="none">
<bt name="int"/>
<Stmt>

</Stmt>
</p>
<Stmt>
<u lb="60" cb="1" le="68" ce="1">
<if lb="61" cb="3" le="61" ce="56">
<xop lb="61" cb="7" le="61" ce="26" kind="||">
<xop lb="61" cb="7" le="61" ce="14" kind="&lt;">
<n32 lb="61" cb="7">
<drx lb="61" cb="7" kind="lvalue" nm="rows"/>
</n32>
<n45 lb="61" cb="14">
<flit/>
</n45>
</xop>
<xop lb="61" cb="19" le="61" ce="26" kind="&lt;">
<n32 lb="61" cb="19">
<drx lb="61" cb="19" kind="lvalue" nm="cols"/>
</n32>
<n45 lb="61" cb="26"/>
</xop>
</xop>
<ce lb="61" cb="29" le="61" ce="56" nbparm="2" id="bf0a0e7d30c19718305066569bf60630_4bdfc08d4302b7e3823b171d5880f65e">
<exp pvirg="true"/>
<n32 lb="61" cb="29">
<drx lb="61" cb="29" kind="lvalue" id="bf0a0e7d30c19718305066569bf60630_4bdfc08d4302b7e3823b171d5880f65e" nm="dDebug"/>
</n32>
<n45 lb="61" cb="37">
<flit/>
</n45>
<n32 lb="61" cb="39">
<n52 lb="61" cb="39">
<slit/>
</n52>
</n32>
</ce>
</if>
<xop lb="62" cb="3" le="62" ce="7" kind="=">
<mex lb="62" cb="3" kind="lvalue" id="7479261a19d8caf3e9083b64a7fc171e_44c90156e6d3be3a5384b958814ba9f0" nm="n" arrow="1">
<n19 lb="62" cb="3"/>
</mex>
<n32 lb="62" cb="7">
<drx lb="62" cb="7" kind="lvalue" nm="rows"/>
</n32>
</xop>
<xop lb="63" cb="3" le="63" ce="7" kind="=">
<mex lb="63" cb="3" kind="lvalue" id="7479261a19d8caf3e9083b64a7fc171e_55d1164524980f21336331fffd4e97be" nm="m" arrow="1">
<n19 lb="63" cb="3"/>
</mex>
<n32 lb="63" cb="7">
<drx lb="63" cb="7" kind="lvalue" nm="cols"/>
</n32>
</xop>
<fx lb="65" cb="3" le="67" ce="3">
<dst lb="65" cb="8" le="65" ce="15">
<exp pvirg="true"/>
<Var nm="i" value="true">
<bt name="int"/>
<n45 lb="65" cb="14"/>
</Var>
</dst>
<xop lb="65" cb="17" le="65" ce="19" kind="&lt;">
<n32 lb="65" cb="17">
<drx lb="65" cb="17" kind="lvalue" nm="i"/>
</n32>
<n32 lb="65" cb="19">
<mex lb="65" cb="19" kind="lvalue" id="7479261a19d8caf3e9083b64a7fc171e_44c90156e6d3be3a5384b958814ba9f0" nm="n" arrow="1">
<n19 lb="65" cb="19"/>
</mex>
</n32>
</xop>
<uo lb="65" cb="22" le="65" ce="23" kind="++">
<drx lb="65" cb="22" kind="lvalue" nm="i"/>
</uo>
<u lb="65" cb="27" le="67" ce="3"/>
</fx>
</u>

</Stmt>
</c>
<d name="~dMatrix" id="fa7b08882ecc2022f1b72573ed8765f8_71629d37f73b3c6cfc5199b39dd7f4b8" file="2" linestart="71" lineend="74" previous="7479261a19d8caf3e9083b64a7fc171e_71629d37f73b3c6cfc5199b39dd7f4b8" access="public" hasbody="true" isdef="true">
<fpt cc="cdecl" proto="void">
<bt name="void"/>
</fpt>
<Stmt>
<u lb="72" cb="1" le="74" ce="1"/>

</Stmt>
</d>
<m name="operator()" id="fa7b08882ecc2022f1b72573ed8765f8_cf79f80319363a0aaf4c233873cbed40" file="2" linestart="77" lineend="81" operator="true" access="public" hasbody="true" isdef="true">
<fpt cc="cdecl" proto="int &amp;">
<lrf>
<bt name="int"/>
</lrf>
</fpt>
<p name="i" proto="int" isLiteral="true" isPrimitive="true" access2="none">
<bt name="int"/>
<Stmt>

</Stmt>
</p>
<p name="j" proto="int" isLiteral="true" isPrimitive="true" access2="none">
<bt name="int"/>
<Stmt>

</Stmt>
</p>
<Stmt>
<u lb="78" cb="1" le="81" ce="1">
<if lb="79" cb="3" le="79" ce="71">
<xop lb="79" cb="7" le="79" ce="40" kind="||">
<xop lb="79" cb="7" le="79" ce="30" kind="||">
<xop lb="79" cb="7" le="79" ce="21" kind="||">
<xop lb="79" cb="7" le="79" ce="11" kind="&lt;">
<n32 lb="79" cb="7">
<drx lb="79" cb="7" kind="lvalue" nm="i"/>
</n32>
<n45 lb="79" cb="11">
<flit/>
</n45>
</xop>
<xop lb="79" cb="16" le="79" ce="21" kind="&gt;=">
<n32 lb="79" cb="16">
<drx lb="79" cb="16" kind="lvalue" nm="i"/>
</n32>
<n32 lb="79" cb="21">
<mex lb="79" cb="21" kind="lvalue" id="7479261a19d8caf3e9083b64a7fc171e_44c90156e6d3be3a5384b958814ba9f0" nm="n" arrow="1">
<n19 lb="79" cb="21"/>
</mex>
</n32>
</xop>
</xop>
<xop lb="79" cb="26" le="79" ce="30" kind="&lt;">
<n32 lb="79" cb="26">
<drx lb="79" cb="26" kind="lvalue" nm="j"/>
</n32>
<n45 lb="79" cb="30"/>
</xop>
</xop>
<xop lb="79" cb="35" le="79" ce="40" kind="&gt;=">
<n32 lb="79" cb="35">
<drx lb="79" cb="35" kind="lvalue" nm="j"/>
</n32>
<n32 lb="79" cb="40">
<mex lb="79" cb="40" kind="lvalue" id="7479261a19d8caf3e9083b64a7fc171e_55d1164524980f21336331fffd4e97be" nm="m" arrow="1">
<n19 lb="79" cb="40"/>
</mex>
</n32>
</xop>
</xop>
<ce lb="79" cb="43" le="79" ce="71" nbparm="2" id="bf0a0e7d30c19718305066569bf60630_4bdfc08d4302b7e3823b171d5880f65e">
<exp pvirg="true"/>
<n32 lb="79" cb="43">
<drx lb="79" cb="43" kind="lvalue" id="bf0a0e7d30c19718305066569bf60630_4bdfc08d4302b7e3823b171d5880f65e" nm="dDebug"/>
</n32>
<n45 lb="79" cb="51"/>
<n32 lb="79" cb="53">
<n52 lb="79" cb="53">
<slit/>
</n52>
</n32>
</ce>
</if>
</u>

</Stmt>
</m>
<m name="operator=" id="fa7b08882ecc2022f1b72573ed8765f8_347d348c596d16733bed75f82e4ea9ee" file="2" linestart="84" lineend="94" previous="7479261a19d8caf3e9083b64a7fc171e_347d348c596d16733bed75f82e4ea9ee" operator="true" access="public" hasbody="true" isdef="true">
<fpt cc="cdecl" proto="void">
<bt name="void"/>
</fpt>
<p name="a" proto="const dMatrix &amp;" isRef="true" isLiteral="true" access2="none">
<lrf>
<QualType const="true">
<rt>
<cr id="7479261a19d8caf3e9083b64a7fc171e_f9c1595ee35ee1df778e88e7e865635a"/>
</rt>
</QualType>
</lrf>
<Stmt>

</Stmt>
</p>
<Stmt>
<u lb="85" cb="1" le="94" ce="1">
<xop lb="87" cb="3" le="87" ce="9" kind="=">
<mex lb="87" cb="3" kind="lvalue" id="7479261a19d8caf3e9083b64a7fc171e_44c90156e6d3be3a5384b958814ba9f0" nm="n" arrow="1">
<n19 lb="87" cb="3"/>
</mex>
<n32 lb="87" cb="7" le="87" ce="9">
<mex lb="87" cb="7" le="87" ce="9" kind="lvalue" id="7479261a19d8caf3e9083b64a7fc171e_44c90156e6d3be3a5384b958814ba9f0" nm="n" point="1">
<drx lb="87" cb="7" kind="lvalue" nm="a"/>
</mex>
</n32>
</xop>
<xop lb="88" cb="3" le="88" ce="9" kind="=">
<mex lb="88" cb="3" kind="lvalue" id="7479261a19d8caf3e9083b64a7fc171e_55d1164524980f21336331fffd4e97be" nm="m" arrow="1">
<n19 lb="88" cb="3"/>
</mex>
<n32 lb="88" cb="7" le="88" ce="9">
<mex lb="88" cb="7" le="88" ce="9" kind="lvalue" id="7479261a19d8caf3e9083b64a7fc171e_55d1164524980f21336331fffd4e97be" nm="m" point="1">
<drx lb="88" cb="7" kind="lvalue" nm="a"/>
</mex>
</n32>
</xop>
<if lb="89" cb="3" le="93" ce="8" else="true" elselb="93" elsecb="8">
<xop lb="89" cb="7" le="89" ce="20" kind="&amp;&amp;">
<xop lb="89" cb="7" le="89" ce="11" kind="&gt;">
<n32 lb="89" cb="7">
<mex lb="89" cb="7" kind="lvalue" id="7479261a19d8caf3e9083b64a7fc171e_44c90156e6d3be3a5384b958814ba9f0" nm="n" arrow="1">
<n19 lb="89" cb="7"/>
</mex>
</n32>
<n45 lb="89" cb="11">
<flit/>
</n45>
</xop>
<xop lb="89" cb="16" le="89" ce="20" kind="&gt;">
<n32 lb="89" cb="16">
<mex lb="89" cb="16" kind="lvalue" id="7479261a19d8caf3e9083b64a7fc171e_55d1164524980f21336331fffd4e97be" nm="m" arrow="1">
<n19 lb="89" cb="16"/>
</mex>
</n32>
<n45 lb="89" cb="20"/>
</xop>
</xop>
<u lb="89" cb="23" le="92" ce="3"/>
<n59 lb="93" cb="8"/>
</if>
</u>

</Stmt>
</m>
<m name="operator=" id="fa7b08882ecc2022f1b72573ed8765f8_89717ef31692fc7e158ce0000e45b73a" file="2" linestart="97" lineend="100" operator="true" access="public" hasbody="true" isdef="true">
<fpt cc="cdecl" proto="void">
<bt name="void"/>
</fpt>
<p name="a" proto="int" isLiteral="true" isPrimitive="true" access2="none">
<bt name="int"/>
<Stmt>

</Stmt>
</p>
<Stmt>
<u lb="98" cb="1" le="100" ce="1"/>

</Stmt>
</m>
<m name="transpose" id="fa7b08882ecc2022f1b72573ed8765f8_e9fb51c814a87360d25726b34bfa1a2e" file="2" linestart="103" lineend="110" previous="7479261a19d8caf3e9083b64a7fc171e_e9fb51c814a87360d25726b34bfa1a2e" access="public" hasbody="true" isdef="true">
<fpt cc="cdecl" proto="dMatrix">
<rt>
<cr id="7479261a19d8caf3e9083b64a7fc171e_f9c1595ee35ee1df778e88e7e865635a"/>
</rt>
</fpt>
<Stmt>
<u lb="104" cb="1" le="110" ce="1">
<dst lb="105" cb="3" le="105" ce="18">
<exp pvirg="true"/>
<Var nm="r" value="true">
<rt>
<cr id="7479261a19d8caf3e9083b64a7fc171e_f9c1595ee35ee1df778e88e7e865635a"/>
</rt>
<n10 lb="105" cb="11" le="105" ce="17">
<typeptr id="7479261a19d8caf3e9083b64a7fc171e_d0e33bd2230dffede970a6ddd07d4164"/>
<temp/>
<n32 lb="105" cb="14">
<mex lb="105" cb="14" kind="lvalue" id="7479261a19d8caf3e9083b64a7fc171e_55d1164524980f21336331fffd4e97be" nm="m" arrow="1">
<n19 lb="105" cb="14"/>
</mex>
</n32>
<n32 lb="105" cb="16">
<mex lb="105" cb="16" kind="lvalue" id="7479261a19d8caf3e9083b64a7fc171e_44c90156e6d3be3a5384b958814ba9f0" nm="n" arrow="1">
<n19 lb="105" cb="16"/>
</mex>
</n32>
</n10>
</Var>
</dst>
<fx lb="106" cb="3" le="108" ce="3">
<dst lb="106" cb="8" le="106" ce="15">
<exp pvirg="true"/>
<Var nm="i" value="true">
<bt name="int"/>
<n45 lb="106" cb="14">
<flit/>
</n45>
</Var>
</dst>
<xop lb="106" cb="17" le="106" ce="19" kind="&lt;">
<n32 lb="106" cb="17">
<drx lb="106" cb="17" kind="lvalue" nm="i"/>
</n32>
<n32 lb="106" cb="19">
<mex lb="106" cb="19" kind="lvalue" id="7479261a19d8caf3e9083b64a7fc171e_44c90156e6d3be3a5384b958814ba9f0" nm="n" arrow="1">
<n19 lb="106" cb="19"/>
</mex>
</n32>
</xop>
<uo lb="106" cb="22" le="106" ce="23" kind="++">
<drx lb="106" cb="22" kind="lvalue" nm="i"/>
</uo>
<u lb="106" cb="27" le="108" ce="3"/>
</fx>
<rx lb="109" cb="3" le="109" ce="10" pvirg="true">
<n10 lb="109" cb="10">
<typeptr id="7479261a19d8caf3e9083b64a7fc171e_ba777c7a74e7632087eba300793e6c0e"/>
<temp/>
<n32 lb="109" cb="10">
<drx lb="109" cb="10" kind="lvalue" nm="r"/>
</n32>
</n10>
</rx>
</u>

</Stmt>
</m>
<m name="select" id="fa7b08882ecc2022f1b72573ed8765f8_0043727f9043270345626b4a132e0b84" file="2" linestart="113" lineend="125" previous="7479261a19d8caf3e9083b64a7fc171e_0043727f9043270345626b4a132e0b84" access="public" hasbody="true" isdef="true">
<fpt cc="cdecl" proto="dMatrix">
<rt>
<cr id="7479261a19d8caf3e9083b64a7fc171e_f9c1595ee35ee1df778e88e7e865635a"/>
</rt>
</fpt>
<p name="np" proto="int" isLiteral="true" isPrimitive="true" access2="none">
<bt name="int"/>
<Stmt>

</Stmt>
</p>
<p name="p" proto="int *" isPtr="true" isLiteral="true" access2="none">
<pt>
<bt name="int"/>
</pt>
<Stmt>

</Stmt>
</p>
<p name="nq" proto="int" isLiteral="true" isPrimitive="true" access2="none">
<bt name="int"/>
<Stmt>

</Stmt>
</p>
<p name="q" proto="int *" isPtr="true" isLiteral="true" access2="none">
<pt>
<bt name="int"/>
</pt>
<Stmt>

</Stmt>
</p>
<Stmt>
<u lb="114" cb="1" le="125" ce="1">
<if lb="115" cb="3" le="115" ce="73">
<xop lb="115" cb="7" le="115" ce="22" kind="||">
<xop lb="115" cb="7" le="115" ce="12" kind="&lt;">
<n32 lb="115" cb="7">
<drx lb="115" cb="7" kind="lvalue" nm="np"/>
</n32>
<n45 lb="115" cb="12">
<flit/>
</n45>
</xop>
<xop lb="115" cb="17" le="115" ce="22" kind="&lt;">
<n32 lb="115" cb="17">
<drx lb="115" cb="17" kind="lvalue" nm="nq"/>
</n32>
<n45 lb="115" cb="22"/>
</xop>
</xop>
<ce lb="115" cb="25" le="115" ce="73" nbparm="2" id="bf0a0e7d30c19718305066569bf60630_4bdfc08d4302b7e3823b171d5880f65e">
<exp pvirg="true"/>
<n32 lb="115" cb="25">
<drx lb="115" cb="25" kind="lvalue" id="bf0a0e7d30c19718305066569bf60630_4bdfc08d4302b7e3823b171d5880f65e" nm="dDebug"/>
</n32>
<n45 lb="115" cb="33">
<flit/>
</n45>
<n32 lb="115" cb="35">
<n52 lb="115" cb="35">
<slit/>
</n52>
</n32>
</ce>
</if>
<dst lb="116" cb="3" le="116" ce="20">
<exp pvirg="true"/>
<Var nm="r" value="true">
<rt>
<cr id="7479261a19d8caf3e9083b64a7fc171e_f9c1595ee35ee1df778e88e7e865635a"/>
</rt>
<n10 lb="116" cb="11" le="116" ce="19">
<typeptr id="7479261a19d8caf3e9083b64a7fc171e_d0e33bd2230dffede970a6ddd07d4164"/>
<temp/>
<n32 lb="116" cb="14">
<drx lb="116" cb="14" kind="lvalue" nm="np"/>
</n32>
<n32 lb="116" cb="17">
<drx lb="116" cb="17" kind="lvalue" nm="nq"/>
</n32>
</n10>
</Var>
</dst>
<fx lb="117" cb="3" le="123" ce="3">
<dst lb="117" cb="8" le="117" ce="15">
<exp pvirg="true"/>
<Var nm="i" value="true">
<bt name="int"/>
<n45 lb="117" cb="14"/>
</Var>
</dst>
<xop lb="117" cb="17" le="117" ce="19" kind="&lt;">
<n32 lb="117" cb="17">
<drx lb="117" cb="17" kind="lvalue" nm="i"/>
</n32>
<n32 lb="117" cb="19">
<drx lb="117" cb="19" kind="lvalue" nm="np"/>
</n32>
</xop>
<uo lb="117" cb="23" le="117" ce="24" kind="++">
<drx lb="117" cb="23" kind="lvalue" nm="i"/>
</uo>
<u lb="117" cb="28" le="123" ce="3">
<fx lb="118" cb="5" le="122" ce="5">
<dst lb="118" cb="10" le="118" ce="17">
<exp pvirg="true"/>
<Var nm="j" value="true">
<bt name="int"/>
<n45 lb="118" cb="16"/>
</Var>
</dst>
<xop lb="118" cb="19" le="118" ce="21" kind="&lt;">
<n32 lb="118" cb="19">
<drx lb="118" cb="19" kind="lvalue" nm="j"/>
</n32>
<n32 lb="118" cb="21">
<drx lb="118" cb="21" kind="lvalue" nm="nq"/>
</n32>
</xop>
<uo lb="118" cb="25" le="118" ce="26" kind="++">
<drx lb="118" cb="25" kind="lvalue" nm="j"/>
</uo>
<u lb="118" cb="30" le="122" ce="5">
<if lb="119" cb="7" le="120" ce="45">
<xop lb="119" cb="11" le="119" ce="56" kind="||">
<xop lb="119" cb="11" le="119" ce="43" kind="||">
<xop lb="119" cb="11" le="119" ce="31" kind="||">
<xop lb="119" cb="11" le="119" ce="18" kind="&lt;">
<n32 lb="119" cb="11" le="119" ce="14">
<n2 lb="119" cb="11" le="119" ce="14">
<exp pvirg="true"/>
<n32 lb="119" cb="11">
<drx lb="119" cb="11" kind="lvalue" nm="p"/>
</n32>
<n32 lb="119" cb="13">
<drx lb="119" cb="13" kind="lvalue" nm="i"/>
</n32>
</n2>
</n32>
<n45 lb="119" cb="18"/>
</xop>
<xop lb="119" cb="23" le="119" ce="31" kind="&gt;=">
<n32 lb="119" cb="23" le="119" ce="26">
<n2 lb="119" cb="23" le="119" ce="26">
<exp pvirg="true"/>
<n32 lb="119" cb="23">
<drx lb="119" cb="23" kind="lvalue" nm="p"/>
</n32>
<n32 lb="119" cb="25">
<drx lb="119" cb="25" kind="lvalue" nm="i"/>
</n32>
</n2>
</n32>
<n32 lb="119" cb="31">
<mex lb="119" cb="31" kind="lvalue" id="7479261a19d8caf3e9083b64a7fc171e_44c90156e6d3be3a5384b958814ba9f0" nm="n" arrow="1">
<n19 lb="119" cb="31"/>
</mex>
</n32>
</xop>
</xop>
<xop lb="119" cb="36" le="119" ce="43" kind="&lt;">
<n32 lb="119" cb="36" le="119" ce="39">
<n2 lb="119" cb="36" le="119" ce="39">
<exp pvirg="true"/>
<n32 lb="119" cb="36">
<drx lb="119" cb="36" kind="lvalue" nm="q"/>
</n32>
<n32 lb="119" cb="38">
<drx lb="119" cb="38" kind="lvalue" nm="i"/>
</n32>
</n2>
</n32>
<n45 lb="119" cb="43"/>
</xop>
</xop>
<xop lb="119" cb="48" le="119" ce="56" kind="&gt;=">
<n32 lb="119" cb="48" le="119" ce="51">
<n2 lb="119" cb="48" le="119" ce="51">
<exp pvirg="true"/>
<n32 lb="119" cb="48">
<drx lb="119" cb="48" kind="lvalue" nm="q"/>
</n32>
<n32 lb="119" cb="50">
<drx lb="119" cb="50" kind="lvalue" nm="i"/>
</n32>
</n2>
</n32>
<n32 lb="119" cb="56">
<mex lb="119" cb="56" kind="lvalue" id="7479261a19d8caf3e9083b64a7fc171e_55d1164524980f21336331fffd4e97be" nm="m" arrow="1">
<n19 lb="119" cb="56"/>
</mex>
</n32>
</xop>
</xop>
<ce lb="120" cb="2" le="120" ce="45" nbparm="2" id="bf0a0e7d30c19718305066569bf60630_4bdfc08d4302b7e3823b171d5880f65e">
<exp pvirg="true"/>
<n32 lb="120" cb="2">
<drx lb="120" cb="2" kind="lvalue" id="bf0a0e7d30c19718305066569bf60630_4bdfc08d4302b7e3823b171d5880f65e" nm="dDebug"/>
</n32>
<n45 lb="120" cb="10"/>
<n32 lb="120" cb="12">
<n52 lb="120" cb="12">
<slit/>
</n52>
</n32>
</ce>
</if>
</u>
</fx>
</u>
</fx>
<rx lb="124" cb="3" le="124" ce="10" pvirg="true">
<n10 lb="124" cb="10">
<typeptr id="7479261a19d8caf3e9083b64a7fc171e_ba777c7a74e7632087eba300793e6c0e"/>
<temp/>
<n32 lb="124" cb="10">
<drx lb="124" cb="10" kind="lvalue" nm="r"/>
</n32>
</n10>
</rx>
</u>

</Stmt>
</m>
<m name="operator+" id="fa7b08882ecc2022f1b72573ed8765f8_b4558ac2716bb7c264e45ebfea551cb6" file="2" linestart="128" lineend="134" previous="7479261a19d8caf3e9083b64a7fc171e_b4558ac2716bb7c264e45ebfea551cb6" operator="true" access="public" hasbody="true" isdef="true">
<fpt cc="cdecl" proto="dMatrix">
<rt>
<cr id="7479261a19d8caf3e9083b64a7fc171e_f9c1595ee35ee1df778e88e7e865635a"/>
</rt>
</fpt>
<p name="a" proto="const dMatrix &amp;" isRef="true" isLiteral="true" access2="none">
<lrf>
<QualType const="true">
<rt>
<cr id="7479261a19d8caf3e9083b64a7fc171e_f9c1595ee35ee1df778e88e7e865635a"/>
</rt>
</QualType>
</lrf>
<Stmt>

</Stmt>
</p>
<Stmt>
<u lb="129" cb="1" le="134" ce="1">
<if lb="130" cb="3" le="130" ce="67">
<xop lb="130" cb="7" le="130" ce="26" kind="||">
<xop lb="130" cb="7" le="130" ce="14" kind="!=">
<n32 lb="130" cb="7">
<mex lb="130" cb="7" kind="lvalue" id="7479261a19d8caf3e9083b64a7fc171e_44c90156e6d3be3a5384b958814ba9f0" nm="n" arrow="1">
<n19 lb="130" cb="7"/>
</mex>
</n32>
<n32 lb="130" cb="12" le="130" ce="14">
<mex lb="130" cb="12" le="130" ce="14" kind="lvalue" id="7479261a19d8caf3e9083b64a7fc171e_44c90156e6d3be3a5384b958814ba9f0" nm="n" point="1">
<drx lb="130" cb="12" kind="lvalue" nm="a"/>
</mex>
</n32>
</xop>
<xop lb="130" cb="19" le="130" ce="26" kind="!=">
<n32 lb="130" cb="19">
<mex lb="130" cb="19" kind="lvalue" id="7479261a19d8caf3e9083b64a7fc171e_55d1164524980f21336331fffd4e97be" nm="m" arrow="1">
<n19 lb="130" cb="19"/>
</mex>
</n32>
<n32 lb="130" cb="24" le="130" ce="26">
<mex lb="130" cb="24" le="130" ce="26" kind="lvalue" id="7479261a19d8caf3e9083b64a7fc171e_55d1164524980f21336331fffd4e97be" nm="m" point="1">
<drx lb="130" cb="24" kind="lvalue" nm="a"/>
</mex>
</n32>
</xop>
</xop>
<ce lb="130" cb="29" le="130" ce="67" nbparm="2" id="bf0a0e7d30c19718305066569bf60630_4bdfc08d4302b7e3823b171d5880f65e">
<exp pvirg="true"/>
<n32 lb="130" cb="29">
<drx lb="130" cb="29" kind="lvalue" id="bf0a0e7d30c19718305066569bf60630_4bdfc08d4302b7e3823b171d5880f65e" nm="dDebug"/>
</n32>
<n45 lb="130" cb="37">
<flit/>
</n45>
<n32 lb="130" cb="39">
<n52 lb="130" cb="39">
<slit/>
</n52>
</n32>
</ce>
</if>
<dst lb="131" cb="3" le="131" ce="18">
<exp pvirg="true"/>
<Var nm="r" value="true">
<rt>
<cr id="7479261a19d8caf3e9083b64a7fc171e_f9c1595ee35ee1df778e88e7e865635a"/>
</rt>
<n10 lb="131" cb="11" le="131" ce="17">
<typeptr id="7479261a19d8caf3e9083b64a7fc171e_d0e33bd2230dffede970a6ddd07d4164"/>
<temp/>
<n32 lb="131" cb="14">
<mex lb="131" cb="14" kind="lvalue" id="7479261a19d8caf3e9083b64a7fc171e_44c90156e6d3be3a5384b958814ba9f0" nm="n" arrow="1">
<n19 lb="131" cb="14"/>
</mex>
</n32>
<n32 lb="131" cb="16">
<mex lb="131" cb="16" kind="lvalue" id="7479261a19d8caf3e9083b64a7fc171e_55d1164524980f21336331fffd4e97be" nm="m" arrow="1">
<n19 lb="131" cb="16"/>
</mex>
</n32>
</n10>
</Var>
</dst>
<rx lb="133" cb="3" le="133" ce="10" pvirg="true">
<n10 lb="133" cb="10">
<typeptr id="7479261a19d8caf3e9083b64a7fc171e_ba777c7a74e7632087eba300793e6c0e"/>
<temp/>
<n32 lb="133" cb="10">
<drx lb="133" cb="10" kind="lvalue" nm="r"/>
</n32>
</n10>
</rx>
</u>

</Stmt>
</m>
<m name="operator-" id="fa7b08882ecc2022f1b72573ed8765f8_6ebb7f263b8afc24fdebc7e3867ae585" file="2" linestart="137" lineend="143" previous="7479261a19d8caf3e9083b64a7fc171e_6ebb7f263b8afc24fdebc7e3867ae585" operator="true" access="public" hasbody="true" isdef="true">
<fpt cc="cdecl" proto="dMatrix">
<rt>
<cr id="7479261a19d8caf3e9083b64a7fc171e_f9c1595ee35ee1df778e88e7e865635a"/>
</rt>
</fpt>
<p name="a" proto="const dMatrix &amp;" isRef="true" isLiteral="true" access2="none">
<lrf>
<QualType const="true">
<rt>
<cr id="7479261a19d8caf3e9083b64a7fc171e_f9c1595ee35ee1df778e88e7e865635a"/>
</rt>
</QualType>
</lrf>
<Stmt>

</Stmt>
</p>
<Stmt>
<u lb="138" cb="1" le="143" ce="1">
<if lb="139" cb="3" le="139" ce="67">
<xop lb="139" cb="7" le="139" ce="26" kind="||">
<xop lb="139" cb="7" le="139" ce="14" kind="!=">
<n32 lb="139" cb="7">
<mex lb="139" cb="7" kind="lvalue" id="7479261a19d8caf3e9083b64a7fc171e_44c90156e6d3be3a5384b958814ba9f0" nm="n" arrow="1">
<n19 lb="139" cb="7"/>
</mex>
</n32>
<n32 lb="139" cb="12" le="139" ce="14">
<mex lb="139" cb="12" le="139" ce="14" kind="lvalue" id="7479261a19d8caf3e9083b64a7fc171e_44c90156e6d3be3a5384b958814ba9f0" nm="n" point="1">
<drx lb="139" cb="12" kind="lvalue" nm="a"/>
</mex>
</n32>
</xop>
<xop lb="139" cb="19" le="139" ce="26" kind="!=">
<n32 lb="139" cb="19">
<mex lb="139" cb="19" kind="lvalue" id="7479261a19d8caf3e9083b64a7fc171e_55d1164524980f21336331fffd4e97be" nm="m" arrow="1">
<n19 lb="139" cb="19"/>
</mex>
</n32>
<n32 lb="139" cb="24" le="139" ce="26">
<mex lb="139" cb="24" le="139" ce="26" kind="lvalue" id="7479261a19d8caf3e9083b64a7fc171e_55d1164524980f21336331fffd4e97be" nm="m" point="1">
<drx lb="139" cb="24" kind="lvalue" nm="a"/>
</mex>
</n32>
</xop>
</xop>
<ce lb="139" cb="29" le="139" ce="67" nbparm="2" id="bf0a0e7d30c19718305066569bf60630_4bdfc08d4302b7e3823b171d5880f65e">
<exp pvirg="true"/>
<n32 lb="139" cb="29">
<drx lb="139" cb="29" kind="lvalue" id="bf0a0e7d30c19718305066569bf60630_4bdfc08d4302b7e3823b171d5880f65e" nm="dDebug"/>
</n32>
<n45 lb="139" cb="37">
<flit/>
</n45>
<n32 lb="139" cb="39">
<n52 lb="139" cb="39">
<slit/>
</n52>
</n32>
</ce>
</if>
<dst lb="140" cb="3" le="140" ce="18">
<exp pvirg="true"/>
<Var nm="r" value="true">
<rt>
<cr id="7479261a19d8caf3e9083b64a7fc171e_f9c1595ee35ee1df778e88e7e865635a"/>
</rt>
<n10 lb="140" cb="11" le="140" ce="17">
<typeptr id="7479261a19d8caf3e9083b64a7fc171e_d0e33bd2230dffede970a6ddd07d4164"/>
<temp/>
<n32 lb="140" cb="14">
<mex lb="140" cb="14" kind="lvalue" id="7479261a19d8caf3e9083b64a7fc171e_44c90156e6d3be3a5384b958814ba9f0" nm="n" arrow="1">
<n19 lb="140" cb="14"/>
</mex>
</n32>
<n32 lb="140" cb="16">
<mex lb="140" cb="16" kind="lvalue" id="7479261a19d8caf3e9083b64a7fc171e_55d1164524980f21336331fffd4e97be" nm="m" arrow="1">
<n19 lb="140" cb="16"/>
</mex>
</n32>
</n10>
</Var>
</dst>
<rx lb="142" cb="3" le="142" ce="10" pvirg="true">
<n10 lb="142" cb="10">
<typeptr id="7479261a19d8caf3e9083b64a7fc171e_ba777c7a74e7632087eba300793e6c0e"/>
<temp/>
<n32 lb="142" cb="10">
<drx lb="142" cb="10" kind="lvalue" nm="r"/>
</n32>
</n10>
</rx>
</u>

</Stmt>
</m>
<m name="operator-" id="fa7b08882ecc2022f1b72573ed8765f8_b2dcc0631f6276797150f2772bf2099f" file="2" linestart="146" lineend="151" previous="7479261a19d8caf3e9083b64a7fc171e_b2dcc0631f6276797150f2772bf2099f" operator="true" access="public" hasbody="true" isdef="true">
<fpt cc="cdecl" proto="dMatrix">
<rt>
<cr id="7479261a19d8caf3e9083b64a7fc171e_f9c1595ee35ee1df778e88e7e865635a"/>
</rt>
</fpt>
<Stmt>
<u lb="147" cb="1" le="151" ce="1">
<dst lb="148" cb="3" le="148" ce="18">
<exp pvirg="true"/>
<Var nm="r" value="true">
<rt>
<cr id="7479261a19d8caf3e9083b64a7fc171e_f9c1595ee35ee1df778e88e7e865635a"/>
</rt>
<n10 lb="148" cb="11" le="148" ce="17">
<typeptr id="7479261a19d8caf3e9083b64a7fc171e_d0e33bd2230dffede970a6ddd07d4164"/>
<temp/>
<n32 lb="148" cb="14">
<mex lb="148" cb="14" kind="lvalue" id="7479261a19d8caf3e9083b64a7fc171e_44c90156e6d3be3a5384b958814ba9f0" nm="n" arrow="1">
<n19 lb="148" cb="14"/>
</mex>
</n32>
<n32 lb="148" cb="16">
<mex lb="148" cb="16" kind="lvalue" id="7479261a19d8caf3e9083b64a7fc171e_55d1164524980f21336331fffd4e97be" nm="m" arrow="1">
<n19 lb="148" cb="16"/>
</mex>
</n32>
</n10>
</Var>
</dst>
<rx lb="150" cb="3" le="150" ce="10" pvirg="true">
<n10 lb="150" cb="10">
<typeptr id="7479261a19d8caf3e9083b64a7fc171e_ba777c7a74e7632087eba300793e6c0e"/>
<temp/>
<n32 lb="150" cb="10">
<drx lb="150" cb="10" kind="lvalue" nm="r"/>
</n32>
</n10>
</rx>
</u>

</Stmt>
</m>
<m name="operator*" id="fa7b08882ecc2022f1b72573ed8765f8_0deb58f2e8e47300aef244c0fdbcfc09" file="2" linestart="154" lineend="166" previous="7479261a19d8caf3e9083b64a7fc171e_0deb58f2e8e47300aef244c0fdbcfc09" operator="true" access="public" hasbody="true" isdef="true">
<fpt cc="cdecl" proto="dMatrix">
<rt>
<cr id="7479261a19d8caf3e9083b64a7fc171e_f9c1595ee35ee1df778e88e7e865635a"/>
</rt>
</fpt>
<p name="a" proto="const dMatrix &amp;" isRef="true" isLiteral="true" access2="none">
<lrf>
<QualType const="true">
<rt>
<cr id="7479261a19d8caf3e9083b64a7fc171e_f9c1595ee35ee1df778e88e7e865635a"/>
</rt>
</QualType>
</lrf>
<Stmt>

</Stmt>
</p>
<Stmt>
<u lb="155" cb="1" le="166" ce="1">
<if lb="156" cb="3" le="156" ce="55">
<xop lb="156" cb="7" le="156" ce="14" kind="!=">
<n32 lb="156" cb="7">
<mex lb="156" cb="7" kind="lvalue" id="7479261a19d8caf3e9083b64a7fc171e_55d1164524980f21336331fffd4e97be" nm="m" arrow="1">
<n19 lb="156" cb="7"/>
</mex>
</n32>
<n32 lb="156" cb="12" le="156" ce="14">
<mex lb="156" cb="12" le="156" ce="14" kind="lvalue" id="7479261a19d8caf3e9083b64a7fc171e_44c90156e6d3be3a5384b958814ba9f0" nm="n" point="1">
<drx lb="156" cb="12" kind="lvalue" nm="a"/>
</mex>
</n32>
</xop>
<ce lb="156" cb="17" le="156" ce="55" nbparm="2" id="bf0a0e7d30c19718305066569bf60630_4bdfc08d4302b7e3823b171d5880f65e">
<exp pvirg="true"/>
<n32 lb="156" cb="17">
<drx lb="156" cb="17" kind="lvalue" id="bf0a0e7d30c19718305066569bf60630_4bdfc08d4302b7e3823b171d5880f65e" nm="dDebug"/>
</n32>
<n45 lb="156" cb="25">
<flit/>
</n45>
<n32 lb="156" cb="27">
<n52 lb="156" cb="27">
<slit/>
</n52>
</n32>
</ce>
</if>
<dst lb="157" cb="3" le="157" ce="20">
<exp pvirg="true"/>
<Var nm="r" value="true">
<rt>
<cr id="7479261a19d8caf3e9083b64a7fc171e_f9c1595ee35ee1df778e88e7e865635a"/>
</rt>
<n10 lb="157" cb="11" le="157" ce="19">
<typeptr id="7479261a19d8caf3e9083b64a7fc171e_d0e33bd2230dffede970a6ddd07d4164"/>
<temp/>
<n32 lb="157" cb="14">
<mex lb="157" cb="14" kind="lvalue" id="7479261a19d8caf3e9083b64a7fc171e_44c90156e6d3be3a5384b958814ba9f0" nm="n" arrow="1">
<n19 lb="157" cb="14"/>
</mex>
</n32>
<n32 lb="157" cb="16" le="157" ce="18">
<mex lb="157" cb="16" le="157" ce="18" kind="lvalue" id="7479261a19d8caf3e9083b64a7fc171e_55d1164524980f21336331fffd4e97be" nm="m" point="1">
<drx lb="157" cb="16" kind="lvalue" nm="a"/>
</mex>
</n32>
</n10>
</Var>
</dst>
<fx lb="158" cb="3" le="164" ce="3">
<dst lb="158" cb="8" le="158" ce="15">
<exp pvirg="true"/>
<Var nm="i" value="true">
<bt name="int"/>
<n45 lb="158" cb="14"/>
</Var>
</dst>
<xop lb="158" cb="17" le="158" ce="19" kind="&lt;">
<n32 lb="158" cb="17">
<drx lb="158" cb="17" kind="lvalue" nm="i"/>
</n32>
<n32 lb="158" cb="19">
<mex lb="158" cb="19" kind="lvalue" id="7479261a19d8caf3e9083b64a7fc171e_44c90156e6d3be3a5384b958814ba9f0" nm="n" arrow="1">
<n19 lb="158" cb="19"/>
</mex>
</n32>
</xop>
<uo lb="158" cb="22" le="158" ce="23" kind="++">
<drx lb="158" cb="22" kind="lvalue" nm="i"/>
</uo>
<u lb="158" cb="27" le="164" ce="3">
<fx lb="159" cb="5" le="163" ce="5">
<dst lb="159" cb="10" le="159" ce="17">
<exp pvirg="true"/>
<Var nm="j" value="true">
<bt name="int"/>
<n45 lb="159" cb="16"/>
</Var>
</dst>
<xop lb="159" cb="19" le="159" ce="23" kind="&lt;">
<n32 lb="159" cb="19">
<drx lb="159" cb="19" kind="lvalue" nm="j"/>
</n32>
<n32 lb="159" cb="21" le="159" ce="23">
<mex lb="159" cb="21" le="159" ce="23" kind="lvalue" id="7479261a19d8caf3e9083b64a7fc171e_55d1164524980f21336331fffd4e97be" nm="m" point="1">
<drx lb="159" cb="21" kind="lvalue" nm="a"/>
</mex>
</n32>
</xop>
<uo lb="159" cb="26" le="159" ce="27" kind="++">
<drx lb="159" cb="26" kind="lvalue" nm="j"/>
</uo>
<u lb="159" cb="31" le="163" ce="5">
<dst lb="160" cb="7" le="160" ce="20">
<exp pvirg="true"/>
<Var nm="sum" value="true">
<bt name="int"/>
</Var>
</dst>
</u>
</fx>
</u>
</fx>
<rx lb="165" cb="3" le="165" ce="10" pvirg="true">
<n10 lb="165" cb="10">
<typeptr id="7479261a19d8caf3e9083b64a7fc171e_ba777c7a74e7632087eba300793e6c0e"/>
<temp/>
<n32 lb="165" cb="10">
<drx lb="165" cb="10" kind="lvalue" nm="r"/>
</n32>
</n10>
</rx>
</u>

</Stmt>
</m>
<m name="operator+=" id="fa7b08882ecc2022f1b72573ed8765f8_03c3e61b81a3281d061f94cc78cfd0c1" file="2" linestart="169" lineend="173" previous="7479261a19d8caf3e9083b64a7fc171e_03c3e61b81a3281d061f94cc78cfd0c1" operator="true" access="public" hasbody="true" isdef="true">
<fpt cc="cdecl" proto="void">
<bt name="void"/>
</fpt>
<p name="a" proto="const dMatrix &amp;" isRef="true" isLiteral="true" access2="none">
<lrf>
<QualType const="true">
<rt>
<cr id="7479261a19d8caf3e9083b64a7fc171e_f9c1595ee35ee1df778e88e7e865635a"/>
</rt>
</QualType>
</lrf>
<Stmt>

</Stmt>
</p>
<Stmt>
<u lb="170" cb="1" le="173" ce="1">
<if lb="171" cb="3" le="171" ce="68">
<xop lb="171" cb="7" le="171" ce="26" kind="||">
<xop lb="171" cb="7" le="171" ce="14" kind="!=">
<n32 lb="171" cb="7">
<mex lb="171" cb="7" kind="lvalue" id="7479261a19d8caf3e9083b64a7fc171e_44c90156e6d3be3a5384b958814ba9f0" nm="n" arrow="1">
<n19 lb="171" cb="7"/>
</mex>
</n32>
<n32 lb="171" cb="12" le="171" ce="14">
<mex lb="171" cb="12" le="171" ce="14" kind="lvalue" id="7479261a19d8caf3e9083b64a7fc171e_44c90156e6d3be3a5384b958814ba9f0" nm="n" point="1">
<drx lb="171" cb="12" kind="lvalue" nm="a"/>
</mex>
</n32>
</xop>
<xop lb="171" cb="19" le="171" ce="26" kind="!=">
<n32 lb="171" cb="19">
<mex lb="171" cb="19" kind="lvalue" id="7479261a19d8caf3e9083b64a7fc171e_55d1164524980f21336331fffd4e97be" nm="m" arrow="1">
<n19 lb="171" cb="19"/>
</mex>
</n32>
<n32 lb="171" cb="24" le="171" ce="26">
<mex lb="171" cb="24" le="171" ce="26" kind="lvalue" id="7479261a19d8caf3e9083b64a7fc171e_55d1164524980f21336331fffd4e97be" nm="m" point="1">
<drx lb="171" cb="24" kind="lvalue" nm="a"/>
</mex>
</n32>
</xop>
</xop>
<ce lb="171" cb="29" le="171" ce="68" nbparm="2" id="bf0a0e7d30c19718305066569bf60630_4bdfc08d4302b7e3823b171d5880f65e">
<exp pvirg="true"/>
<n32 lb="171" cb="29">
<drx lb="171" cb="29" kind="lvalue" id="bf0a0e7d30c19718305066569bf60630_4bdfc08d4302b7e3823b171d5880f65e" nm="dDebug"/>
</n32>
<n45 lb="171" cb="37">
<flit/>
</n45>
<n32 lb="171" cb="39">
<n52 lb="171" cb="39">
<slit/>
</n52>
</n32>
</ce>
</if>
</u>

</Stmt>
</m>
<m name="operator-=" id="fa7b08882ecc2022f1b72573ed8765f8_4b1c9727a8e58d2c1a95377ac7d43b7e" file="2" linestart="176" lineend="180" previous="7479261a19d8caf3e9083b64a7fc171e_4b1c9727a8e58d2c1a95377ac7d43b7e" operator="true" access="public" hasbody="true" isdef="true">
<fpt cc="cdecl" proto="void">
<bt name="void"/>
</fpt>
<p name="a" proto="const dMatrix &amp;" isRef="true" isLiteral="true" access2="none">
<lrf>
<QualType const="true">
<rt>
<cr id="7479261a19d8caf3e9083b64a7fc171e_f9c1595ee35ee1df778e88e7e865635a"/>
</rt>
</QualType>
</lrf>
<Stmt>

</Stmt>
</p>
<Stmt>
<u lb="177" cb="1" le="180" ce="1">
<if lb="178" cb="3" le="178" ce="68">
<xop lb="178" cb="7" le="178" ce="26" kind="||">
<xop lb="178" cb="7" le="178" ce="14" kind="!=">
<n32 lb="178" cb="7">
<mex lb="178" cb="7" kind="lvalue" id="7479261a19d8caf3e9083b64a7fc171e_44c90156e6d3be3a5384b958814ba9f0" nm="n" arrow="1">
<n19 lb="178" cb="7"/>
</mex>
</n32>
<n32 lb="178" cb="12" le="178" ce="14">
<mex lb="178" cb="12" le="178" ce="14" kind="lvalue" id="7479261a19d8caf3e9083b64a7fc171e_44c90156e6d3be3a5384b958814ba9f0" nm="n" point="1">
<drx lb="178" cb="12" kind="lvalue" nm="a"/>
</mex>
</n32>
</xop>
<xop lb="178" cb="19" le="178" ce="26" kind="!=">
<n32 lb="178" cb="19">
<mex lb="178" cb="19" kind="lvalue" id="7479261a19d8caf3e9083b64a7fc171e_55d1164524980f21336331fffd4e97be" nm="m" arrow="1">
<n19 lb="178" cb="19"/>
</mex>
</n32>
<n32 lb="178" cb="24" le="178" ce="26">
<mex lb="178" cb="24" le="178" ce="26" kind="lvalue" id="7479261a19d8caf3e9083b64a7fc171e_55d1164524980f21336331fffd4e97be" nm="m" point="1">
<drx lb="178" cb="24" kind="lvalue" nm="a"/>
</mex>
</n32>
</xop>
</xop>
<ce lb="178" cb="29" le="178" ce="68" nbparm="2" id="bf0a0e7d30c19718305066569bf60630_4bdfc08d4302b7e3823b171d5880f65e">
<exp pvirg="true"/>
<n32 lb="178" cb="29">
<drx lb="178" cb="29" kind="lvalue" id="bf0a0e7d30c19718305066569bf60630_4bdfc08d4302b7e3823b171d5880f65e" nm="dDebug"/>
</n32>
<n45 lb="178" cb="37">
<flit/>
</n45>
<n32 lb="178" cb="39">
<n52 lb="178" cb="39">
<slit/>
</n52>
</n32>
</ce>
</if>
</u>

</Stmt>
</m>
<m name="clearUpperTriangle" id="fa7b08882ecc2022f1b72573ed8765f8_86138a2690ba66e5adb6983d55effff7" file="2" linestart="183" lineend="189" previous="7479261a19d8caf3e9083b64a7fc171e_86138a2690ba66e5adb6983d55effff7" access="public" hasbody="true" isdef="true">
<fpt cc="cdecl" proto="void">
<bt name="void"/>
</fpt>
<Stmt>
<u lb="184" cb="1" le="189" ce="1">
<if lb="185" cb="3" le="185" ce="77">
<xop lb="185" cb="7" le="185" ce="12" kind="!=">
<n32 lb="185" cb="7">
<mex lb="185" cb="7" kind="lvalue" id="7479261a19d8caf3e9083b64a7fc171e_44c90156e6d3be3a5384b958814ba9f0" nm="n" arrow="1">
<n19 lb="185" cb="7"/>
</mex>
</n32>
<n32 lb="185" cb="12">
<mex lb="185" cb="12" kind="lvalue" id="7479261a19d8caf3e9083b64a7fc171e_55d1164524980f21336331fffd4e97be" nm="m" arrow="1">
<n19 lb="185" cb="12"/>
</mex>
</n32>
</xop>
<ce lb="185" cb="15" le="185" ce="77" nbparm="2" id="bf0a0e7d30c19718305066569bf60630_4bdfc08d4302b7e3823b171d5880f65e">
<exp pvirg="true"/>
<n32 lb="185" cb="15">
<drx lb="185" cb="15" kind="lvalue" id="bf0a0e7d30c19718305066569bf60630_4bdfc08d4302b7e3823b171d5880f65e" nm="dDebug"/>
</n32>
<n45 lb="185" cb="23">
<flit/>
</n45>
<n32 lb="185" cb="25">
<n52 lb="185" cb="25">
<slit/>
</n52>
</n32>
</ce>
</if>
<fx lb="186" cb="3" le="188" ce="3">
<dst lb="186" cb="8" le="186" ce="15">
<exp pvirg="true"/>
<Var nm="i" value="true">
<bt name="int"/>
<n45 lb="186" cb="14"/>
</Var>
</dst>
<xop lb="186" cb="17" le="186" ce="19" kind="&lt;">
<n32 lb="186" cb="17">
<drx lb="186" cb="17" kind="lvalue" nm="i"/>
</n32>
<n32 lb="186" cb="19">
<mex lb="186" cb="19" kind="lvalue" id="7479261a19d8caf3e9083b64a7fc171e_44c90156e6d3be3a5384b958814ba9f0" nm="n" arrow="1">
<n19 lb="186" cb="19"/>
</mex>
</n32>
</xop>
<uo lb="186" cb="22" le="186" ce="23" kind="++">
<drx lb="186" cb="22" kind="lvalue" nm="i"/>
</uo>
<u lb="186" cb="27" le="188" ce="3"/>
</fx>
</u>

</Stmt>
</m>
<m name="clearLowerTriangle" id="fa7b08882ecc2022f1b72573ed8765f8_a1bf0d41960cf3ee1a4c899cfb1a981d" file="2" linestart="192" lineend="198" previous="7479261a19d8caf3e9083b64a7fc171e_a1bf0d41960cf3ee1a4c899cfb1a981d" access="public" hasbody="true" isdef="true">
<fpt cc="cdecl" proto="void">
<bt name="void"/>
</fpt>
<Stmt>
<u lb="193" cb="1" le="198" ce="1">
<if lb="194" cb="3" le="194" ce="77">
<xop lb="194" cb="7" le="194" ce="12" kind="!=">
<n32 lb="194" cb="7">
<mex lb="194" cb="7" kind="lvalue" id="7479261a19d8caf3e9083b64a7fc171e_44c90156e6d3be3a5384b958814ba9f0" nm="n" arrow="1">
<n19 lb="194" cb="7"/>
</mex>
</n32>
<n32 lb="194" cb="12">
<mex lb="194" cb="12" kind="lvalue" id="7479261a19d8caf3e9083b64a7fc171e_55d1164524980f21336331fffd4e97be" nm="m" arrow="1">
<n19 lb="194" cb="12"/>
</mex>
</n32>
</xop>
<ce lb="194" cb="15" le="194" ce="77" nbparm="2" id="bf0a0e7d30c19718305066569bf60630_4bdfc08d4302b7e3823b171d5880f65e">
<exp pvirg="true"/>
<n32 lb="194" cb="15">
<drx lb="194" cb="15" kind="lvalue" id="bf0a0e7d30c19718305066569bf60630_4bdfc08d4302b7e3823b171d5880f65e" nm="dDebug"/>
</n32>
<n45 lb="194" cb="23">
<flit/>
</n45>
<n32 lb="194" cb="25">
<n52 lb="194" cb="25">
<slit/>
</n52>
</n32>
</ce>
</if>
<fx lb="195" cb="3" le="197" ce="3">
<dst lb="195" cb="8" le="195" ce="15">
<exp pvirg="true"/>
<Var nm="i" value="true">
<bt name="int"/>
<n45 lb="195" cb="14"/>
</Var>
</dst>
<xop lb="195" cb="17" le="195" ce="19" kind="&lt;">
<n32 lb="195" cb="17">
<drx lb="195" cb="17" kind="lvalue" nm="i"/>
</n32>
<n32 lb="195" cb="19">
<mex lb="195" cb="19" kind="lvalue" id="7479261a19d8caf3e9083b64a7fc171e_44c90156e6d3be3a5384b958814ba9f0" nm="n" arrow="1">
<n19 lb="195" cb="19"/>
</mex>
</n32>
</xop>
<uo lb="195" cb="22" le="195" ce="23" kind="++">
<drx lb="195" cb="22" kind="lvalue" nm="i"/>
</uo>
<u lb="195" cb="27" le="197" ce="3"/>
</fx>
</u>

</Stmt>
</m>
<m name="makeRandom" id="fa7b08882ecc2022f1b72573ed8765f8_0d06d8d119cd8c3de45af699c18331d4" file="2" linestart="201" lineend="207" access="public" hasbody="true" isdef="true">
<fpt cc="cdecl" proto="void">
<bt name="void"/>
</fpt>
<p name="range" proto="int" isLiteral="true" isPrimitive="true" access2="none">
<bt name="int"/>
<Stmt>

</Stmt>
</p>
<Stmt>
<u lb="202" cb="1" le="207" ce="1">
<fx lb="203" cb="3" le="206" ce="3">
<dst lb="203" cb="8" le="203" ce="15">
<exp pvirg="true"/>
<Var nm="i" value="true">
<bt name="int"/>
<n45 lb="203" cb="14">
<flit/>
</n45>
</Var>
</dst>
<xop lb="203" cb="17" le="203" ce="19" kind="&lt;">
<n32 lb="203" cb="17">
<drx lb="203" cb="17" kind="lvalue" nm="i"/>
</n32>
<n32 lb="203" cb="19">
<mex lb="203" cb="19" kind="lvalue" id="7479261a19d8caf3e9083b64a7fc171e_44c90156e6d3be3a5384b958814ba9f0" nm="n" arrow="1">
<n19 lb="203" cb="19"/>
</mex>
</n32>
</xop>
<uo lb="203" cb="22" le="203" ce="23" kind="++">
<drx lb="203" cb="22" kind="lvalue" nm="i"/>
</uo>
<u lb="203" cb="27" le="206" ce="3"/>
</fx>
</u>

</Stmt>
</m>
<m name="print" id="fa7b08882ecc2022f1b72573ed8765f8_7a46d278bff5bc23325cc8e10fd40e8d" file="2" linestart="210" lineend="216" previous="7479261a19d8caf3e9083b64a7fc171e_7a46d278bff5bc23325cc8e10fd40e8d" access="public" hasbody="true" isdef="true">
<fpt cc="cdecl" proto="void">
<bt name="void"/>
</fpt>
<p name="fmt" proto="const char *" isPtr="true" isLiteral="true" init="true" access2="none">
<pt>
<QualType const="true">
<bt name="char"/>
</QualType>
</pt>
<Stmt>
<n32 lb="66" cb="33">
<n52 lb="66" cb="33">
<slit/>
</n52>
</n32>

</Stmt>
</p>
<p name="f" proto="FILE *" isPtr="true" isLiteral="true" init="true" access2="none">
<pt>
<Tdef>
<ety>
<rt>
<cr id="551d34c4201f45e199ffddc38791c29c_9b75e14604360f7936837e5997e12eba"/>
</rt>
</ety>
</Tdef>
</pt>
<Stmt>
<n46 lb="66" cb="52" le="66" ce="52">
<exp pvirg="true"/>
<uo lb="66" cb="52" le="66" ce="52" kind="&amp;">
<n2 lb="66" cb="52" le="66" ce="52">
<exp pvirg="true"/>
<n32 lb="66" cb="52">
<drx lb="66" cb="52" kind="lvalue" id="551d34c4201f45e199ffddc38791c29c_9ae2eabed9862d8d1fb4bba66f2f2197" nm="_iob"/>
</n32>
<n45 lb="66" cb="52">
<flit/>
</n45>
</n2>
</uo>
</n46>

</Stmt>
</p>
<Stmt>
<u lb="211" cb="1" le="216" ce="1">
<fx lb="212" cb="3" le="215" ce="3">
<dst lb="212" cb="8" le="212" ce="15">
<exp pvirg="true"/>
<Var nm="i" value="true">
<bt name="int"/>
<n45 lb="212" cb="14">
<flit/>
</n45>
</Var>
</dst>
<xop lb="212" cb="17" le="212" ce="19" kind="&lt;">
<n32 lb="212" cb="17">
<drx lb="212" cb="17" kind="lvalue" nm="i"/>
</n32>
<n32 lb="212" cb="19">
<mex lb="212" cb="19" kind="lvalue" id="7479261a19d8caf3e9083b64a7fc171e_44c90156e6d3be3a5384b958814ba9f0" nm="n" arrow="1">
<n19 lb="212" cb="19"/>
</mex>
</n32>
</xop>
<uo lb="212" cb="22" le="212" ce="23" kind="++">
<drx lb="212" cb="22" kind="lvalue" nm="i"/>
</uo>
<u lb="212" cb="27" le="215" ce="3">
<ce lb="214" cb="5" le="214" ce="20" nbparm="2" id="551d34c4201f45e199ffddc38791c29c_af6d79effa222eff445da5668b78cca0">
<exp pvirg="true"/>
<n32 lb="214" cb="5">
<drx lb="214" cb="5" kind="lvalue" id="551d34c4201f45e199ffddc38791c29c_af6d79effa222eff445da5668b78cca0" nm="fprintf"/>
</n32>
<n32 lb="214" cb="14">
<drx lb="214" cb="14" kind="lvalue" nm="f"/>
</n32>
<n32 lb="214" cb="16">
<n52 lb="214" cb="16">
<slit/>
</n52>
</n32>
</ce>
</u>
</fx>
</u>

</Stmt>
</m>
<m name="maxDifference" id="fa7b08882ecc2022f1b72573ed8765f8_18fad9f1f540cb8a0033a82e6088c375" file="2" linestart="219" lineend="230" access="public" hasbody="true" isdef="true">
<fpt cc="cdecl" proto="int">
<bt name="int"/>
</fpt>
<p name="a" proto="const dMatrix &amp;" isRef="true" isLiteral="true" access2="none">
<lrf>
<QualType const="true">
<rt>
<cr id="7479261a19d8caf3e9083b64a7fc171e_f9c1595ee35ee1df778e88e7e865635a"/>
</rt>
</QualType>
</lrf>
<Stmt>

</Stmt>
</p>
<Stmt>
<u lb="220" cb="1" le="230" ce="1">
<if lb="221" cb="3" le="221" ce="74">
<xop lb="221" cb="7" le="221" ce="26" kind="||">
<xop lb="221" cb="7" le="221" ce="14" kind="!=">
<n32 lb="221" cb="7">
<mex lb="221" cb="7" kind="lvalue" id="7479261a19d8caf3e9083b64a7fc171e_44c90156e6d3be3a5384b958814ba9f0" nm="n" arrow="1">
<n19 lb="221" cb="7"/>
</mex>
</n32>
<n32 lb="221" cb="12" le="221" ce="14">
<mex lb="221" cb="12" le="221" ce="14" kind="lvalue" id="7479261a19d8caf3e9083b64a7fc171e_44c90156e6d3be3a5384b958814ba9f0" nm="n" point="1">
<drx lb="221" cb="12" kind="lvalue" nm="a"/>
</mex>
</n32>
</xop>
<xop lb="221" cb="19" le="221" ce="26" kind="!=">
<n32 lb="221" cb="19">
<mex lb="221" cb="19" kind="lvalue" id="7479261a19d8caf3e9083b64a7fc171e_55d1164524980f21336331fffd4e97be" nm="m" arrow="1">
<n19 lb="221" cb="19"/>
</mex>
</n32>
<n32 lb="221" cb="24" le="221" ce="26">
<mex lb="221" cb="24" le="221" ce="26" kind="lvalue" id="7479261a19d8caf3e9083b64a7fc171e_55d1164524980f21336331fffd4e97be" nm="m" point="1">
<drx lb="221" cb="24" kind="lvalue" nm="a"/>
</mex>
</n32>
</xop>
</xop>
<ce lb="221" cb="29" le="221" ce="74" nbparm="2" id="bf0a0e7d30c19718305066569bf60630_4bdfc08d4302b7e3823b171d5880f65e">
<exp pvirg="true"/>
<n32 lb="221" cb="29">
<drx lb="221" cb="29" kind="lvalue" id="bf0a0e7d30c19718305066569bf60630_4bdfc08d4302b7e3823b171d5880f65e" nm="dDebug"/>
</n32>
<n45 lb="221" cb="37">
<flit/>
</n45>
<n32 lb="221" cb="39">
<n52 lb="221" cb="39">
<slit/>
</n52>
</n32>
</ce>
</if>
<dst lb="222" cb="3" le="222" ce="16">
<exp pvirg="true"/>
<Var nm="max" value="true">
<bt name="int"/>
</Var>
</dst>
<fx lb="223" cb="3" le="228" ce="3">
<dst lb="223" cb="8" le="223" ce="15">
<exp pvirg="true"/>
<Var nm="i" value="true">
<bt name="int"/>
<n45 lb="223" cb="14"/>
</Var>
</dst>
<xop lb="223" cb="17" le="223" ce="19" kind="&lt;">
<n32 lb="223" cb="17">
<drx lb="223" cb="17" kind="lvalue" nm="i"/>
</n32>
<n32 lb="223" cb="19">
<mex lb="223" cb="19" kind="lvalue" id="7479261a19d8caf3e9083b64a7fc171e_44c90156e6d3be3a5384b958814ba9f0" nm="n" arrow="1">
<n19 lb="223" cb="19"/>
</mex>
</n32>
</xop>
<uo lb="223" cb="22" le="223" ce="23" kind="++">
<drx lb="223" cb="22" kind="lvalue" nm="i"/>
</uo>
<u lb="223" cb="27" le="228" ce="3">
<fx lb="224" cb="5" le="227" ce="5">
<dst lb="224" cb="10" le="224" ce="17">
<exp pvirg="true"/>
<Var nm="j" value="true">
<bt name="int"/>
<n45 lb="224" cb="16"/>
</Var>
</dst>
<xop lb="224" cb="19" le="224" ce="21" kind="&lt;">
<n32 lb="224" cb="19">
<drx lb="224" cb="19" kind="lvalue" nm="j"/>
</n32>
<n32 lb="224" cb="21">
<mex lb="224" cb="21" kind="lvalue" id="7479261a19d8caf3e9083b64a7fc171e_55d1164524980f21336331fffd4e97be" nm="m" arrow="1">
<n19 lb="224" cb="21"/>
</mex>
</n32>
</xop>
<uo lb="224" cb="24" le="224" ce="25" kind="++">
<drx lb="224" cb="24" kind="lvalue" nm="j"/>
</uo>
<u lb="224" cb="29" le="227" ce="5">
<dst lb="225" cb="7" le="225" ce="54">
<exp pvirg="true"/>
<Var nm="diff" value="true">
<bt name="int"/>
</Var>
</dst>
</u>
</fx>
</u>
</fx>
</u>

</Stmt>
</m>
</tun>
</Root>
